Workbook

Sheet KPI
A1: KPI di servizio: Puntualità e Accuratezza
A2: L'OTIF è diviso in due KPI distinti. Ogni cliente può richiederne uno, entrambi o con soglie diverse.
A4: KPI | B4: Cosa misura | C4: Fattore che lo influenza | D4: Dettaglio
A5: Puntualità (On Time) | B5: % di consegne arrivate entro la data o la fascia oraria concordata | C5: Capacità di trasporto | D5: Mezzi e autisti disponibili rispetto agli ordini
C6: Tratta | D6: Distanza e tipo di percorso: città, autostrada, valichi alpini
C7: Eventi | D7: Neve, scioperi, blocchi stradali, guasti
C8: Persone | D8: Abilità Operazioni del manager e del Direttore Operativo
C9: Tecnologia | D9: Telematica, pianificazione delle rotte
C10: Vettori esterni | D10: Affidabilità dei padroncini e dei vettori in subvezione
A11: Accuratezza (In Full) | B11: % di ordini consegnati completi e corretti: articoli e quantità giusti, senza danni | C11: Magazzinieri | D11: Morale ed esperienza
C12: Saturazione | D12: Oltre la soglia del foglio Regole gli errori aumentano
C13: Tecnologia | D13: Lettori barcode, WMS, pick-to-light, robot
C14: Persone | D14: Abilità del manager del magazzino
C15: Tipo di merce | D15: Fragile, refrigerata o a lotti è più difficile da gestire

Sheet Clienti
A1: Requisiti dei clienti
A2: Celle in blu su sfondo giallo: da modificare. Soglia vuota = KPI non richiesto. I valori "attuali" sono esempi per provare gli esiti.
A4: Cliente | B4: Settore | C4: Soglia puntualità | D4: Soglia accuratezza | E4: Perché | F4: Puntualità attuale (esempio) | G4: Accuratezza attuale (esempio) | H4: Esito puntualità | I4: Esito accuratezza | J4: Stato complessivo
A5: Esselonga | B5: GDO freschi | C5: 0.98 | D5: 0.95 | E5: Gli scaffali vuoti al mattino sono un disastro | F5: 0.975 | G5: 0.96 | H5: =IF(C5="","Non richiesto",IF(F5>=C5,"Sopra soglia",IF(F5>=C5-Regole!$B$4,"Leggermente sotto","Molto sotto"))) -> Leggermente sotto | I5: =IF(D5="","Non richiesto",IF(G5>=D5,"Sopra soglia",IF(G5>=D5-Regole!$B$4,"Leggermente sotto","Molto sotto"))) -> Sopra soglia | J5: =IF(OR(H5="Molto sotto",I5="Molto sotto"),"Rischio penali",IF(OR(H5="Leggermente sotto",I5="Leggermente sotto"),"Soddisfazione in calo","In regola")) -> Soddisfazione in calo
A6: ElettroUnieuri | B6: Elettronica di consumo | C6: 0.9 | D6: 0.99 | E6: Un frigo sbagliato o rotto costa caro | F6: 0.93 | G6: 0.955 | H6: =IF(C6="","Non richiesto",IF(F6>=C6,"Sopra soglia",IF(F6>=C6-Regole!$B$4,"Leggermente sotto","Molto sotto"))) -> Sopra soglia | I6: =IF(D6="","Non richiesto",IF(G6>=D6,"Sopra soglia",IF(G6>=D6-Regole!$B$4,"Leggermente sotto","Molto sotto"))) -> Molto sotto | J6: =IF(OR(H6="Molto sotto",I6="Molto sotto"),"Rischio penali",IF(OR(H6="Leggermente sotto",I6="Leggermente sotto"),"Soddisfazione in calo","In regola")) -> Rischio penali
A7: Pastificio Rummolo | B7: Alimentare secco | C7: 0.92 | E7: Pasta secca: conta solo che arrivi | F7: 0.95 | G7: 0.97 | H7: =IF(C7="","Non richiesto",IF(F7>=C7,"Sopra soglia",IF(F7>=C7-Regole!$B$4,"Leggermente sotto","Molto sotto"))) -> Sopra soglia | I7: =IF(D7="","Non richiesto",IF(G7>=D7,"Sopra soglia",IF(G7>=D7-Regole!$B$4,"Leggermente sotto","Molto sotto"))) -> Non richiesto | J7: =IF(OR(H7="Molto sotto",I7="Molto sotto"),"Rischio penali",IF(OR(H7="Leggermente sotto",I7="Leggermente sotto"),"Soddisfazione in calo","In regola")) -> In regola
A8: FarmaSpa | B8: Farmaceutico | C8: 0.97 | D8: 0.995 | E8: Lotti e scadenze tracciati: cliente difficilissimo | F8: 0.97 | G8: 0.99 | H8: =IF(C8="","Non richiesto",IF(F8>=C8,"Sopra soglia",IF(F8>=C8-Regole!$B$4,"Leggermente sotto","Molto sotto"))) -> Sopra soglia | I8: =IF(D8="","Non richiesto",IF(G8>=D8,"Sopra soglia",IF(G8>=D8-Regole!$B$4,"Leggermente sotto","Molto sotto"))) -> Leggermente sotto | J8: =IF(OR(H8="Molto sotto",I8="Molto sotto"),"Rischio penali",IF(OR(H8="Leggermente sotto",I8="Leggermente sotto"),"Soddisfazione in calo","In regola")) -> Soddisfazione in calo

Sheet Regole
A1: Regole dei KPI
A3: Parametro | B3: Valore | C3: Note
A4: Margine "leggermente sotto" (punti %) | B4: 0.02 | C4: Ipotesi di design: sotto la soglia fino a questo margine = "Leggermente sotto"; oltre = "Molto sotto".
A5: Saturazione oltre cui aumentano gli errori | B5: 0.85 | C5: Ipotesi di design usata per l'accuratezza (vedi foglio KPI).
A7: Esito | B7: Effetto sul cliente
A8: Sopra soglia | B8: La soddisfazione sale; possibili bonus o ampliamenti del contratto.
A9: Leggermente sotto | B9: La soddisfazione cala.
A10: Molto sotto | B10: Penali economiche; se dura più mesi, rischio di mancato rinnovo.
A11: Non richiesto | B11: Il KPI non è nel contratto: non incide sulla soddisfazione.

Sheet Personaggi
A1: Personaggi
A2: Abilità di base + modificatori dei talenti = valore finale (limitato tra 0 e 20). I talenti si scelgono dall'elenco del foglio Talenti. Celle in blu: da modificare.
A4: Nome | B4: Età | C4: Gruppo | D4: Ruolo | E4: Provincia | F4: Talento 1 | G4: Talento 2 | H4: Talento 3 | I4: Operazioni base | J4: Precisione base | K4: Negoziazione base | L4: Leadership base | M4: Amministrazione base | N4: Innovazione base | O4: Operazioni | P4: Precisione | Q4: Negoziazione | R4: Leadership | S4: Amministrazione | T4: Innovazione | U4: Tenuta allo stress | V4: Biografia
A5: Gino Bertolotti | B5: 52 | C5: CEO giocabile | D5: Titolare, ex padroncino | E5: Alessandria | F5: Un milione di km al volante | G5: Allergico al gestionale | H5: Dialetto stretto | I5: 13 | J5: 9 | K5: 7 | L5: 11 | M5: 6 | N5: 8 | O5: =MAX(0,MIN(20,I5+IFERROR(INDEX(Talenti!$B$5:$B$24,MATCH(F5,Talenti!$A$5:$A$24,0)),0)+IFERROR(INDEX(Talenti!$B$5:$B$24,MATCH(G5,Talenti!$A$5:$A$24,0)),0)+IFERROR(INDEX(Talenti!$B$5:$B$24,MATCH(H5,Talenti!$A$5:$A$24,0)),0))) -> 17 | P5: =MAX(0,MIN(20,J5+IFERROR(INDEX(Talenti!$C$5:$C$24,MATCH(F5,Talenti!$A$5:$A$24,0)),0)+IFERROR(INDEX(Talenti!$C$5:$C$24,MATCH(G5,Talenti!$A$5:$A$24,0)),0)+IFERROR(INDEX(Talenti!$C$5:$C$24,MATCH(H5,Talenti!$A$5:$A$24,0)),0))) -> 9 | Q5: =MAX(0,MIN(20,K5+IFERROR(INDEX(Talenti!$D$5:$D$24,MATCH(F5,Talenti!$A$5:$A$24,0)),0)+IFERROR(INDEX(Talenti!$D$5:$D$24,MATCH(G5,Talenti!$A$5:$A$24,0)),0)+IFERROR(INDEX(Talenti!$D$5:$D$24,MATCH(H5,Talenti!$A$5:$A$24,0)),0))) -> 5 | R5: =MAX(0,MIN(20,L5+IFERROR(INDEX(Talenti!$E$5:$E$24,MATCH(F5,Talenti!$A$5:$A$24,0)),0)+IFERROR(INDEX(Talenti!$E$5:$E$24,MATCH(G5,Talenti!$A$5:$A$24,0)),0)+IFERROR(INDEX(Talenti!$E$5:$E$24,MATCH(H5,Talenti!$A$5:$A$24,0)),0))) -> 14 | S5: =MAX(0,MIN(20,M5+IFERROR(INDEX(Talenti!$F$5:$F$24,MATCH(F5,Talenti!$A$5:$A$24,0)),0)+IFERROR(INDEX(Talenti!$F$5:$F$24,MATCH(G5,Talenti!$A$5:$A$24,0)),0)+IFERROR(INDEX(Talenti!$F$5:$F$24,MATCH(H5,Talenti!$A$5:$A$24,0)),0))) -> 6 | T5: =MAX(0,MIN(20,N5+IFERROR(INDEX(Talenti!$G$5:$G$24,MATCH(F5,Talenti!$A$5:$A$24,0)),0)+IFERROR(INDEX(Talenti!$G$5:$G$24,MATCH(G5,Talenti!$A$5:$A$24,0)),0)+IFERROR(INDEX(Talenti!$G$5:$G$24,MATCH(H5,Talenti!$A$5:$A$24,0)),0))) -> 2 | U5: =50+IFERROR(INDEX(Talenti!$H$5:$H$24,MATCH(F5,Talenti!$A$5:$A$24,0)),0)+IFERROR(INDEX(Talenti!$H$5:$H$24,MATCH(G5,Talenti!$A$5:$A$24,0)),0)+IFERROR(INDEX(Talenti!$H$5:$H$24,MATCH(H5,Talenti!$A$5:$A$24,0)),0) -> 50 | V5: Trent'anni sulle strade d'Europa, poi il capannone di Rivalta Scrivia comprato con la liquidazione e un mutuo. Conosce ogni casello dell'A7 e diffida di tutto ciò che ha una presa elettrica.
A6: Edoardo Ferretti | B6: 31 | C6: CEO giocabile | D6: Figlio del fondatore | E6: Milano | F6: Laureato in Bocconi | G6: Papà ha sempre ragione | H6: Sempre al telefono | I6: 7 | J6: 8 | K6: 10 | L6: 8 | M6: 9 | N6: 10 | O6: =MAX(0,MIN(20,I6+IFERROR(INDEX(Talenti!$B$5:$B$24,MATCH(F6,Talenti!$A$5:$A$24,0)),0)+IFERROR(INDEX(Talenti!$B$5:$B$24,MATCH(G6,Talenti!$A$5:$A$24,0)),0)+IFERROR(INDEX(Talenti!$B$5:$B$24,MATCH(H6,Talenti!$A$5:$A$24,0)),0))) -> 6 | P6: =MAX(0,MIN(20,J6+IFERROR(INDEX(Talenti!$C$5:$C$24,MATCH(F6,Talenti!$A$5:$A$24,0)),0)+IFERROR(INDEX(Talenti!$C$5:$C$24,MATCH(G6,Talenti!$A$5:$A$24,0)),0)+IFERROR(INDEX(Talenti!$C$5:$C$24,MATCH(H6,Talenti!$A$5:$A$24,0)),0))) -> 7 | Q6: =MAX(0,MIN(20,K6+IFERROR(INDEX(Talenti!$D$5:$D$24,MATCH(F6,Talenti!$A$5:$A$24,0)),0)+IFERROR(INDEX(Talenti!$D$5:$D$24,MATCH(G6,Talenti!$A$5:$A$24,0)),0)+IFERROR(INDEX(Talenti!$D$5:$D$24,MATCH(H6,Talenti!$A$5:$A$24,0)),0))) -> 13 | R6: =MAX(0,MIN(20,L6+IFERROR(INDEX(Talenti!$E$5:$E$24,MATCH(F6,Talenti!$A$5:$A$24,0)),0)+IFERROR(INDEX(Talenti!$E$5:$E$24,MATCH(G6,Talenti!$A$5:$A$24,0)),0)+IFERROR(INDEX(Talenti!$E$5:$E$24,MATCH(H6,Talenti!$A$5:$A$24,0)),0))) -> 6 | S6: =MAX(0,MIN(20,M6+IFERROR(INDEX(Talenti!$F$5:$F$24,MATCH(F6,Talenti!$A$5:$A$24,0)),0)+IFERROR(INDEX(Talenti!$F$5:$F$24,MATCH(G6,Talenti!$A$5:$A$24,0)),0)+IFERROR(INDEX(Talenti!$F$5:$F$24,MATCH(H6,Talenti!$A$5:$A$24,0)),0))) -> 12 | T6: =MAX(0,MIN(20,N6+IFERROR(INDEX(Talenti!$G$5:$G$24,MATCH(F6,Talenti!$A$5:$A$24,0)),0)+IFERROR(INDEX(Talenti!$G$5:$G$24,MATCH(G6,Talenti!$A$5:$A$24,0)),0)+IFERROR(INDEX(Talenti!$G$5:$G$24,MATCH(H6,Talenti!$A$5:$A$24,0)),0))) -> 10 | U6: =50+IFERROR(INDEX(Talenti!$H$5:$H$24,MATCH(F6,Talenti!$A$5:$A$24,0)),0)+IFERROR(INDEX(Talenti!$H$5:$H$24,MATCH(G6,Talenti!$A$5:$A$24,0)),0)+IFERROR(INDEX(Talenti!$H$5:$H$24,MATCH(H6,Talenti!$A$5:$A$24,0)),0) -> 40 | V6: Ha ereditato il magazzino di Pioltello e un padre che passa "solo per un caffè" tutti i giorni alle 8. Vuole dimostrare di valere più del cognome.
A7: Valeria Conti | B7: 44 | C7: CEO giocabile | D7: Ex manager di multinazionale | E7: Novara | F7: Parla per acronimi | G7: Stacanovista | H7: Cena col buyer | I7: 11 | J7: 10 | K7: 12 | L7: 8 | M7: 10 | N7: 9 | O7: =MAX(0,MIN(20,I7+IFERROR(INDEX(Talenti!$B$5:$B$24,MATCH(F7,Talenti!$A$5:$A$24,0)),0)+IFERROR(INDEX(Talenti!$B$5:$B$24,MATCH(G7,Talenti!$A$5:$A$24,0)),0)+IFERROR(INDEX(Talenti!$B$5:$B$24,MATCH(H7,Talenti!$A$5:$A$24,0)),0))) -> 13 | P7: =MAX(0,MIN(20,J7+IFERROR(INDEX(Talenti!$C$5:$C$24,MATCH(F7,Talenti!$A$5:$A$24,0)),0)+IFERROR(INDEX(Talenti!$C$5:$C$24,MATCH(G7,Talenti!$A$5:$A$24,0)),0)+IFERROR(INDEX(Talenti!$C$5:$C$24,MATCH(H7,Talenti!$A$5:$A$24,0)),0))) -> 10 | Q7: =MAX(0,MIN(20,K7+IFERROR(INDEX(Talenti!$D$5:$D$24,MATCH(F7,Talenti!$A$5:$A$24,0)),0)+IFERROR(INDEX(Talenti!$D$5:$D$24,MATCH(G7,Talenti!$A$5:$A$24,0)),0)+IFERROR(INDEX(Talenti!$D$5:$D$24,MATCH(H7,Talenti!$A$5:$A$24,0)),0))) -> 18 | R7: =MAX(0,MIN(20,L7+IFERROR(INDEX(Talenti!$E$5:$E$24,MATCH(F7,Talenti!$A$5:$A$24,0)),0)+IFERROR(INDEX(Talenti!$E$5:$E$24,MATCH(G7,Talenti!$A$5:$A$24,0)),0)+IFERROR(INDEX(Talenti!$E$5:$E$24,MATCH(H7,Talenti!$A$5:$A$24,0)),0))) -> 5 | S7: =MAX(0,MIN(20,M7+IFERROR(INDEX(Talenti!$F$5:$F$24,MATCH(F7,Talenti!$A$5:$A$24,0)),0)+IFERROR(INDEX(Talenti!$F$5:$F$24,MATCH(G7,Talenti!$A$5:$A$24,0)),0)+IFERROR(INDEX(Talenti!$F$5:$F$24,MATCH(H7,Talenti!$A$5:$A$24,0)),0))) -> 10 | T7: =MAX(0,MIN(20,N7+IFERROR(INDEX(Talenti!$G$5:$G$24,MATCH(F7,Talenti!$A$5:$A$24,0)),0)+IFERROR(INDEX(Talenti!$G$5:$G$24,MATCH(G7,Talenti!$A$5:$A$24,0)),0)+IFERROR(INDEX(Talenti!$G$5:$G$24,MATCH(H7,Talenti!$A$5:$A$24,0)),0))) -> 9 | U7: =50+IFERROR(INDEX(Talenti!$H$5:$H$24,MATCH(F7,Talenti!$A$5:$A$24,0)),0)+IFERROR(INDEX(Talenti!$H$5:$H$24,MATCH(G7,Talenti!$A$5:$A$24,0)),0)+IFERROR(INDEX(Talenti!$H$5:$H$24,MATCH(H7,Talenti!$A$5:$A$24,0)),0) -> 25 | V7: Quindici anni di slide e KPI in una multinazionale. Licenziata in una ristrutturazione, ha deciso di fare da sé. Dorme quattro ore a notte e lo considera un vantaggio competitivo.
A8: Marco Pellegrino | B8: 36 | C8: CEO giocabile | D8: Ingegnere gestionale | E8: Genova | F8: Excel-dipendente | G8: Parla con i robot | H8: Calma olimpica | I8: 9 | J8: 10 | K8: 5 | L8: 8 | M8: 9 | N8: 14 | O8: =MAX(0,MIN(20,I8+IFERROR(INDEX(Talenti!$B$5:$B$24,MATCH(F8,Talenti!$A$5:$A$24,0)),0)+IFERROR(INDEX(Talenti!$B$5:$B$24,MATCH(G8,Talenti!$A$5:$A$24,0)),0)+IFERROR(INDEX(Talenti!$B$5:$B$24,MATCH(H8,Talenti!$A$5:$A$24,0)),0))) -> 9 | P8: =MAX(0,MIN(20,J8+IFERROR(INDEX(Talenti!$C$5:$C$24,MATCH(F8,Talenti!$A$5:$A$24,0)),0)+IFERROR(INDEX(Talenti!$C$5:$C$24,MATCH(G8,Talenti!$A$5:$A$24,0)),0)+IFERROR(INDEX(Talenti!$C$5:$C$24,MATCH(H8,Talenti!$A$5:$A$24,0)),0))) -> 13 | Q8: =MAX(0,MIN(20,K8+IFERROR(INDEX(Talenti!$D$5:$D$24,MATCH(F8,Talenti!$A$5:$A$24,0)),0)+IFERROR(INDEX(Talenti!$D$5:$D$24,MATCH(G8,Talenti!$A$5:$A$24,0)),0)+IFERROR(INDEX(Talenti!$D$5:$D$24,MATCH(H8,Talenti!$A$5:$A$24,0)),0))) -> 5 | R8: =MAX(0,MIN(20,L8+IFERROR(INDEX(Talenti!$E$5:$E$24,MATCH(F8,Talenti!$A$5:$A$24,0)),0)+IFERROR(INDEX(Talenti!$E$5:$E$24,MATCH(G8,Talenti!$A$5:$A$24,0)),0)+IFERROR(INDEX(Talenti!$E$5:$E$24,MATCH(H8,Talenti!$A$5:$A$24,0)),0))) -> 5 | S8: =MAX(0,MIN(20,M8+IFERROR(INDEX(Talenti!$F$5:$F$24,MATCH(F8,Talenti!$A$5:$A$24,0)),0)+IFERROR(INDEX(Talenti!$F$5:$F$24,MATCH(G8,Talenti!$A$5:$A$24,0)),0)+IFERROR(INDEX(Talenti!$F$5:$F$24,MATCH(H8,Talenti!$A$5:$A$24,0)),0))) -> 11 | T8: =MAX(0,MIN(20,N8+IFERROR(INDEX(Talenti!$G$5:$G$24,MATCH(F8,Talenti!$A$5:$A$24,0)),0)+IFERROR(INDEX(Talenti!$G$5:$G$24,MATCH(G8,Talenti!$A$5:$A$24,0)),0)+IFERROR(INDEX(Talenti!$G$5:$G$24,MATCH(H8,Talenti!$A$5:$A$24,0)),0))) -> 17 | U8: =50+IFERROR(INDEX(Talenti!$H$5:$H$24,MATCH(F8,Talenti!$A$5:$A$24,0)),0)+IFERROR(INDEX(Talenti!$H$5:$H$24,MATCH(G8,Talenti!$A$5:$A$24,0)),0)+IFERROR(INDEX(Talenti!$H$5:$H$24,MATCH(H8,Talenti!$A$5:$A$24,0)),0) -> 70 | V8: Ha progettato magazzini automatici per altri, ora ne vuole uno suo. Il piccolo deposito di Voltri è il prototipo: ogni pallet ha un codice, ogni codice ha un foglio Excel.
A9: Rosa Brambati | B9: 47 | C9: Manager disponibile | D9: Manager di magazzino | E9: Lodi | F9: Ex sindacalista | G9: Mano larga | I9: 12 | J9: 11 | K9: 6 | L9: 12 | M9: 7 | N9: 6 | O9: =MAX(0,MIN(20,I9+IFERROR(INDEX(Talenti!$B$5:$B$24,MATCH(F9,Talenti!$A$5:$A$24,0)),0)+IFERROR(INDEX(Talenti!$B$5:$B$24,MATCH(G9,Talenti!$A$5:$A$24,0)),0)+IFERROR(INDEX(Talenti!$B$5:$B$24,MATCH(H9,Talenti!$A$5:$A$24,0)),0))) -> 12 | P9: =MAX(0,MIN(20,J9+IFERROR(INDEX(Talenti!$C$5:$C$24,MATCH(F9,Talenti!$A$5:$A$24,0)),0)+IFERROR(INDEX(Talenti!$C$5:$C$24,MATCH(G9,Talenti!$A$5:$A$24,0)),0)+IFERROR(INDEX(Talenti!$C$5:$C$24,MATCH(H9,Talenti!$A$5:$A$24,0)),0))) -> 11 | Q9: =MAX(0,MIN(20,K9+IFERROR(INDEX(Talenti!$D$5:$D$24,MATCH(F9,Talenti!$A$5:$A$24,0)),0)+IFERROR(INDEX(Talenti!$D$5:$D$24,MATCH(G9,Talenti!$A$5:$A$24,0)),0)+IFERROR(INDEX(Talenti!$D$5:$D$24,MATCH(H9,Talenti!$A$5:$A$24,0)),0))) -> 7 | R9: =MAX(0,MIN(20,L9+IFERROR(INDEX(Talenti!$E$5:$E$24,MATCH(F9,Talenti!$A$5:$A$24,0)),0)+IFERROR(INDEX(Talenti!$E$5:$E$24,MATCH(G9,Talenti!$A$5:$A$24,0)),0)+IFERROR(INDEX(Talenti!$E$5:$E$24,MATCH(H9,Talenti!$A$5:$A$24,0)),0))) -> 17 | S9: =MAX(0,MIN(20,M9+IFERROR(INDEX(Talenti!$F$5:$F$24,MATCH(F9,Talenti!$A$5:$A$24,0)),0)+IFERROR(INDEX(Talenti!$F$5:$F$24,MATCH(G9,Talenti!$A$5:$A$24,0)),0)+IFERROR(INDEX(Talenti!$F$5:$F$24,MATCH(H9,Talenti!$A$5:$A$24,0)),0))) -> 5 | T9: =MAX(0,MIN(20,N9+IFERROR(INDEX(Talenti!$G$5:$G$24,MATCH(F9,Talenti!$A$5:$A$24,0)),0)+IFERROR(INDEX(Talenti!$G$5:$G$24,MATCH(G9,Talenti!$A$5:$A$24,0)),0)+IFERROR(INDEX(Talenti!$G$5:$G$24,MATCH(H9,Talenti!$A$5:$A$24,0)),0))) -> 6 | U9: =50+IFERROR(INDEX(Talenti!$H$5:$H$24,MATCH(F9,Talenti!$A$5:$A$24,0)),0)+IFERROR(INDEX(Talenti!$H$5:$H$24,MATCH(G9,Talenti!$A$5:$A$24,0)),0)+IFERROR(INDEX(Talenti!$H$5:$H$24,MATCH(H9,Talenti!$A$5:$A$24,0)),0) -> 50 | V9: Ha iniziato sul muletto, ha guidato la RSU per dieci anni. I magazzinieri la seguirebbero ovunque, i commercialisti un po' meno.
A10: Salvatore "Totò" Esposito | B10: 58 | C10: Manager disponibile | D10: Capo traffico | E10: Milano | F10: Conosce tutti al bar | G10: Sempre al telefono | I10: 14 | J10: 8 | K10: 10 | L10: 9 | M10: 6 | N10: 5 | O10: =MAX(0,MIN(20,I10+IFERROR(INDEX(Talenti!$B$5:$B$24,MATCH(F10,Talenti!$A$5:$A$24,0)),0)+IFERROR(INDEX(Talenti!$B$5:$B$24,MATCH(G10,Talenti!$A$5:$A$24,0)),0)+IFERROR(INDEX(Talenti!$B$5:$B$24,MATCH(H10,Talenti!$A$5:$A$24,0)),0))) -> 14 | P10: =MAX(0,MIN(20,J10+IFERROR(INDEX(Talenti!$C$5:$C$24,MATCH(F10,Talenti!$A$5:$A$24,0)),0)+IFERROR(INDEX(Talenti!$C$5:$C$24,MATCH(G10,Talenti!$A$5:$A$24,0)),0)+IFERROR(INDEX(Talenti!$C$5:$C$24,MATCH(H10,Talenti!$A$5:$A$24,0)),0))) -> 7 | Q10: =MAX(0,MIN(20,K10+IFERROR(INDEX(Talenti!$D$5:$D$24,MATCH(F10,Talenti!$A$5:$A$24,0)),0)+IFERROR(INDEX(Talenti!$D$5:$D$24,MATCH(G10,Talenti!$A$5:$A$24,0)),0)+IFERROR(INDEX(Talenti!$D$5:$D$24,MATCH(H10,Talenti!$A$5:$A$24,0)),0))) -> 13 | R10: =MAX(0,MIN(20,L10+IFERROR(INDEX(Talenti!$E$5:$E$24,MATCH(F10,Talenti!$A$5:$A$24,0)),0)+IFERROR(INDEX(Talenti!$E$5:$E$24,MATCH(G10,Talenti!$A$5:$A$24,0)),0)+IFERROR(INDEX(Talenti!$E$5:$E$24,MATCH(H10,Talenti!$A$5:$A$24,0)),0))) -> 11 | S10: =MAX(0,MIN(20,M10+IFERROR(INDEX(Talenti!$F$5:$F$24,MATCH(F10,Talenti!$A$5:$A$24,0)),0)+IFERROR(INDEX(Talenti!$F$5:$F$24,MATCH(G10,Talenti!$A$5:$A$24,0)),0)+IFERROR(INDEX(Talenti!$F$5:$F$24,MATCH(H10,Talenti!$A$5:$A$24,0)),0))) -> 6 | T10: =MAX(0,MIN(20,N10+IFERROR(INDEX(Talenti!$G$5:$G$24,MATCH(F10,Talenti!$A$5:$A$24,0)),0)+IFERROR(INDEX(Talenti!$G$5:$G$24,MATCH(G10,Talenti!$A$5:$A$24,0)),0)+IFERROR(INDEX(Talenti!$G$5:$G$24,MATCH(H10,Talenti!$A$5:$A$24,0)),0))) -> 5 | U10: =50+IFERROR(INDEX(Talenti!$H$5:$H$24,MATCH(F10,Talenti!$A$5:$A$24,0)),0)+IFERROR(INDEX(Talenti!$H$5:$H$24,MATCH(G10,Talenti!$A$5:$A$24,0)),0)+IFERROR(INDEX(Talenti!$H$5:$H$24,MATCH(H10,Talenti!$A$5:$A$24,0)),0) -> 45 | V10: Trasferito da Napoli nel 1979, conosce ogni padroncino della provincia per nome e soprannome. Ha tre cellulari e li usa tutti.
A11: Chiara Ferraris | B11: 29 | C11: Manager disponibile | D11: Manager junior | E11: Torino | F11: Excel-dipendente | G11: Ansia da prestazione | I11: 9 | J11: 13 | K11: 7 | L11: 6 | M11: 11 | N11: 11 | O11: =MAX(0,MIN(20,I11+IFERROR(INDEX(Talenti!$B$5:$B$24,MATCH(F11,Talenti!$A$5:$A$24,0)),0)+IFERROR(INDEX(Talenti!$B$5:$B$24,MATCH(G11,Talenti!$A$5:$A$24,0)),0)+IFERROR(INDEX(Talenti!$B$5:$B$24,MATCH(H11,Talenti!$A$5:$A$24,0)),0))) -> 9 | P11: =MAX(0,MIN(20,J11+IFERROR(INDEX(Talenti!$C$5:$C$24,MATCH(F11,Talenti!$A$5:$A$24,0)),0)+IFERROR(INDEX(Talenti!$C$5:$C$24,MATCH(G11,Talenti!$A$5:$A$24,0)),0)+IFERROR(INDEX(Talenti!$C$5:$C$24,MATCH(H11,Talenti!$A$5:$A$24,0)),0))) -> 18 | Q11: =MAX(0,MIN(20,K11+IFERROR(INDEX(Talenti!$D$5:$D$24,MATCH(F11,Talenti!$A$5:$A$24,0)),0)+IFERROR(INDEX(Talenti!$D$5:$D$24,MATCH(G11,Talenti!$A$5:$A$24,0)),0)+IFERROR(INDEX(Talenti!$D$5:$D$24,MATCH(H11,Talenti!$A$5:$A$24,0)),0))) -> 7 | R11: =MAX(0,MIN(20,L11+IFERROR(INDEX(Talenti!$E$5:$E$24,MATCH(F11,Talenti!$A$5:$A$24,0)),0)+IFERROR(INDEX(Talenti!$E$5:$E$24,MATCH(G11,Talenti!$A$5:$A$24,0)),0)+IFERROR(INDEX(Talenti!$E$5:$E$24,MATCH(H11,Talenti!$A$5:$A$24,0)),0))) -> 4 | S11: =MAX(0,MIN(20,M11+IFERROR(INDEX(Talenti!$F$5:$F$24,MATCH(F11,Talenti!$A$5:$A$24,0)),0)+IFERROR(INDEX(Talenti!$F$5:$F$24,MATCH(G11,Talenti!$A$5:$A$24,0)),0)+IFERROR(INDEX(Talenti!$F$5:$F$24,MATCH(H11,Talenti!$A$5:$A$24,0)),0))) -> 13 | T11: =MAX(0,MIN(20,N11+IFERROR(INDEX(Talenti!$G$5:$G$24,MATCH(F11,Talenti!$A$5:$A$24,0)),0)+IFERROR(INDEX(Talenti!$G$5:$G$24,MATCH(G11,Talenti!$A$5:$A$24,0)),0)+IFERROR(INDEX(Talenti!$G$5:$G$24,MATCH(H11,Talenti!$A$5:$A$24,0)),0))) -> 11 | U11: =50+IFERROR(INDEX(Talenti!$H$5:$H$24,MATCH(F11,Talenti!$A$5:$A$24,0)),0)+IFERROR(INDEX(Talenti!$H$5:$H$24,MATCH(G11,Talenti!$A$5:$A$24,0)),0)+IFERROR(INDEX(Talenti!$H$5:$H$24,MATCH(H11,Talenti!$A$5:$A$24,0)),0) -> 30 | V11: Laurea al Politecnico, due stage, un master. Prepara report impeccabili, ma un ritardo di un camion le rovina la settimana.
A12: Davide Rinaldi | B12: 39 | C12: Manager disponibile | D12: Manager di magazzino | E12: Bergamo | F12: Stacanovista | G12: Braccino corto | I12: 13 | J12: 10 | K12: 7 | L12: 8 | M12: 9 | N12: 8 | O12: =MAX(0,MIN(20,I12+IFERROR(INDEX(Talenti!$B$5:$B$24,MATCH(F12,Talenti!$A$5:$A$24,0)),0)+IFERROR(INDEX(Talenti!$B$5:$B$24,MATCH(G12,Talenti!$A$5:$A$24,0)),0)+IFERROR(INDEX(Talenti!$B$5:$B$24,MATCH(H12,Talenti!$A$5:$A$24,0)),0))) -> 15 | P12: =MAX(0,MIN(20,J12+IFERROR(INDEX(Talenti!$C$5:$C$24,MATCH(F12,Talenti!$A$5:$A$24,0)),0)+IFERROR(INDEX(Talenti!$C$5:$C$24,MATCH(G12,Talenti!$A$5:$A$24,0)),0)+IFERROR(INDEX(Talenti!$C$5:$C$24,MATCH(H12,Talenti!$A$5:$A$24,0)),0))) -> 10 | Q12: =MAX(0,MIN(20,K12+IFERROR(INDEX(Talenti!$D$5:$D$24,MATCH(F12,Talenti!$A$5:$A$24,0)),0)+IFERROR(INDEX(Talenti!$D$5:$D$24,MATCH(G12,Talenti!$A$5:$A$24,0)),0)+IFERROR(INDEX(Talenti!$D$5:$D$24,MATCH(H12,Talenti!$A$5:$A$24,0)),0))) -> 7 | R12: =MAX(0,MIN(20,L12+IFERROR(INDEX(Talenti!$E$5:$E$24,MATCH(F12,Talenti!$A$5:$A$24,0)),0)+IFERROR(INDEX(Talenti!$E$5:$E$24,MATCH(G12,Talenti!$A$5:$A$24,0)),0)+IFERROR(INDEX(Talenti!$E$5:$E$24,MATCH(H12,Talenti!$A$5:$A$24,0)),0))) -> 6 | S12: =MAX(0,MIN(20,M12+IFERROR(INDEX(Talenti!$F$5:$F$24,MATCH(F12,Talenti!$A$5:$A$24,0)),0)+IFERROR(INDEX(Talenti!$F$5:$F$24,MATCH(G12,Talenti!$A$5:$A$24,0)),0)+IFERROR(INDEX(Talenti!$F$5:$F$24,MATCH(H12,Talenti!$A$5:$A$24,0)),0))) -> 12 | T12: =MAX(0,MIN(20,N12+IFERROR(INDEX(Talenti!$G$5:$G$24,MATCH(F12,Talenti!$A$5:$A$24,0)),0)+IFERROR(INDEX(Talenti!$G$5:$G$24,MATCH(G12,Talenti!$A$5:$A$24,0)),0)+IFERROR(INDEX(Talenti!$G$5:$G$24,MATCH(H12,Talenti!$A$5:$A$24,0)),0))) -> 8 | U12: =50+IFERROR(INDEX(Talenti!$H$5:$H$24,MATCH(F12,Talenti!$A$5:$A$24,0)),0)+IFERROR(INDEX(Talenti!$H$5:$H$24,MATCH(G12,Talenti!$A$5:$A$24,0)),0)+IFERROR(INDEX(Talenti!$H$5:$H$24,MATCH(H12,Talenti!$A$5:$A$24,0)),0) -> 35 | V12: Ha portato un magazzino di Orio dal 70% al 99% di accuratezza. Nessuno sa come, nessuno ha avuto un aumento.
A13: Luca Mazzoleni | B13: 33 | C13: Manager disponibile | D13: Responsabile tecnologia | E13: Brescia | F13: Parla con i robot | G13: Insonne | I13: 8 | J13: 10 | K13: 5 | L13: 6 | M13: 8 | N13: 15 | O13: =MAX(0,MIN(20,I13+IFERROR(INDEX(Talenti!$B$5:$B$24,MATCH(F13,Talenti!$A$5:$A$24,0)),0)+IFERROR(INDEX(Talenti!$B$5:$B$24,MATCH(G13,Talenti!$A$5:$A$24,0)),0)+IFERROR(INDEX(Talenti!$B$5:$B$24,MATCH(H13,Talenti!$A$5:$A$24,0)),0))) -> 6 | P13: =MAX(0,MIN(20,J13+IFERROR(INDEX(Talenti!$C$5:$C$24,MATCH(F13,Talenti!$A$5:$A$24,0)),0)+IFERROR(INDEX(Talenti!$C$5:$C$24,MATCH(G13,Talenti!$A$5:$A$24,0)),0)+IFERROR(INDEX(Talenti!$C$5:$C$24,MATCH(H13,Talenti!$A$5:$A$24,0)),0))) -> 8 | Q13: =MAX(0,MIN(20,K13+IFERROR(INDEX(Talenti!$D$5:$D$24,MATCH(F13,Talenti!$A$5:$A$24,0)),0)+IFERROR(INDEX(Talenti!$D$5:$D$24,MATCH(G13,Talenti!$A$5:$A$24,0)),0)+IFERROR(INDEX(Talenti!$D$5:$D$24,MATCH(H13,Talenti!$A$5:$A$24,0)),0))) -> 5 | R13: =MAX(0,MIN(20,L13+IFERROR(INDEX(Talenti!$E$5:$E$24,MATCH(F13,Talenti!$A$5:$A$24,0)),0)+IFERROR(INDEX(Talenti!$E$5:$E$24,MATCH(G13,Talenti!$A$5:$A$24,0)),0)+IFERROR(INDEX(Talenti!$E$5:$E$24,MATCH(H13,Talenti!$A$5:$A$24,0)),0))) -> 4 | S13: =MAX(0,MIN(20,M13+IFERROR(INDEX(Talenti!$F$5:$F$24,MATCH(F13,Talenti!$A$5:$A$24,0)),0)+IFERROR(INDEX(Talenti!$F$5:$F$24,MATCH(G13,Talenti!$A$5:$A$24,0)),0)+IFERROR(INDEX(Talenti!$F$5:$F$24,MATCH(H13,Talenti!$A$5:$A$24,0)),0))) -> 8 | T13: =MAX(0,MIN(20,N13+IFERROR(INDEX(Talenti!$G$5:$G$24,MATCH(F13,Talenti!$A$5:$A$24,0)),0)+IFERROR(INDEX(Talenti!$G$5:$G$24,MATCH(G13,Talenti!$A$5:$A$24,0)),0)+IFERROR(INDEX(Talenti!$G$5:$G$24,MATCH(H13,Talenti!$A$5:$A$24,0)),0))) -> 18 | U13: =50+IFERROR(INDEX(Talenti!$H$5:$H$24,MATCH(F13,Talenti!$A$5:$A$24,0)),0)+IFERROR(INDEX(Talenti!$H$5:$H$24,MATCH(G13,Talenti!$A$5:$A$24,0)),0)+IFERROR(INDEX(Talenti!$H$5:$H$24,MATCH(H13,Talenti!$A$5:$A$24,0)),0) -> 40 | V13: Programma di notte, installa di giorno. Chiama i robot del magazzino per nome.
A14: Franca Gallo | B14: 61 | C14: Manager disponibile | D14: Responsabile amministrazione | E14: Alessandria | F14: Calma olimpica | G14: Braccino corto | I14: 7 | J14: 13 | K14: 8 | L14: 9 | M14: 14 | N14: 4 | O14: =MAX(0,MIN(20,I14+IFERROR(INDEX(Talenti!$B$5:$B$24,MATCH(F14,Talenti!$A$5:$A$24,0)),0)+IFERROR(INDEX(Talenti!$B$5:$B$24,MATCH(G14,Talenti!$A$5:$A$24,0)),0)+IFERROR(INDEX(Talenti!$B$5:$B$24,MATCH(H14,Talenti!$A$5:$A$24,0)),0))) -> 7 | P14: =MAX(0,MIN(20,J14+IFERROR(INDEX(Talenti!$C$5:$C$24,MATCH(F14,Talenti!$A$5:$A$24,0)),0)+IFERROR(INDEX(Talenti!$C$5:$C$24,MATCH(G14,Talenti!$A$5:$A$24,0)),0)+IFERROR(INDEX(Talenti!$C$5:$C$24,MATCH(H14,Talenti!$A$5:$A$24,0)),0))) -> 13 | Q14: =MAX(0,MIN(20,K14+IFERROR(INDEX(Talenti!$D$5:$D$24,MATCH(F14,Talenti!$A$5:$A$24,0)),0)+IFERROR(INDEX(Talenti!$D$5:$D$24,MATCH(G14,Talenti!$A$5:$A$24,0)),0)+IFERROR(INDEX(Talenti!$D$5:$D$24,MATCH(H14,Talenti!$A$5:$A$24,0)),0))) -> 8 | R14: =MAX(0,MIN(20,L14+IFERROR(INDEX(Talenti!$E$5:$E$24,MATCH(F14,Talenti!$A$5:$A$24,0)),0)+IFERROR(INDEX(Talenti!$E$5:$E$24,MATCH(G14,Talenti!$A$5:$A$24,0)),0)+IFERROR(INDEX(Talenti!$E$5:$E$24,MATCH(H14,Talenti!$A$5:$A$24,0)),0))) -> 8 | S14: =MAX(0,MIN(20,M14+IFERROR(INDEX(Talenti!$F$5:$F$24,MATCH(F14,Talenti!$A$5:$A$24,0)),0)+IFERROR(INDEX(Talenti!$F$5:$F$24,MATCH(G14,Talenti!$A$5:$A$24,0)),0)+IFERROR(INDEX(Talenti!$F$5:$F$24,MATCH(H14,Talenti!$A$5:$A$24,0)),0))) -> 17 | T14: =MAX(0,MIN(20,N14+IFERROR(INDEX(Talenti!$G$5:$G$24,MATCH(F14,Talenti!$A$5:$A$24,0)),0)+IFERROR(INDEX(Talenti!$G$5:$G$24,MATCH(G14,Talenti!$A$5:$A$24,0)),0)+IFERROR(INDEX(Talenti!$G$5:$G$24,MATCH(H14,Talenti!$A$5:$A$24,0)),0))) -> 4 | U14: =50+IFERROR(INDEX(Talenti!$H$5:$H$24,MATCH(F14,Talenti!$A$5:$A$24,0)),0)+IFERROR(INDEX(Talenti!$H$5:$H$24,MATCH(G14,Talenti!$A$5:$A$24,0)),0)+IFERROR(INDEX(Talenti!$H$5:$H$24,MATCH(H14,Talenti!$A$5:$A$24,0)),0) -> 70 | V14: Ha visto passare la lira, l'euro e tre gestionali. Le fatture le controlla ancora a mano, una per una, e non sbaglia mai.
A15: Klaus Effizienz | B15: 55 | C15: CEO concorrente | D15: CEO di Logistix Global | E15: Milano | F15: Parla per acronimi | G15: Calma olimpica | I15: 15 | J15: 14 | K15: 14 | L15: 9 | M15: 15 | N15: 13 | O15: =MAX(0,MIN(20,I15+IFERROR(INDEX(Talenti!$B$5:$B$24,MATCH(F15,Talenti!$A$5:$A$24,0)),0)+IFERROR(INDEX(Talenti!$B$5:$B$24,MATCH(G15,Talenti!$A$5:$A$24,0)),0)+IFERROR(INDEX(Talenti!$B$5:$B$24,MATCH(H15,Talenti!$A$5:$A$24,0)),0))) -> 15 | P15: =MAX(0,MIN(20,J15+IFERROR(INDEX(Talenti!$C$5:$C$24,MATCH(F15,Talenti!$A$5:$A$24,0)),0)+IFERROR(INDEX(Talenti!$C$5:$C$24,MATCH(G15,Talenti!$A$5:$A$24,0)),0)+IFERROR(INDEX(Talenti!$C$5:$C$24,MATCH(H15,Talenti!$A$5:$A$24,0)),0))) -> 14 | Q15: =MAX(0,MIN(20,K15+IFERROR(INDEX(Talenti!$D$5:$D$24,MATCH(F15,Talenti!$A$5:$A$24,0)),0)+IFERROR(INDEX(Talenti!$D$5:$D$24,MATCH(G15,Talenti!$A$5:$A$24,0)),0)+IFERROR(INDEX(Talenti!$D$5:$D$24,MATCH(H15,Talenti!$A$5:$A$24,0)),0))) -> 16 | R15: =MAX(0,MIN(20,L15+IFERROR(INDEX(Talenti!$E$5:$E$24,MATCH(F15,Talenti!$A$5:$A$24,0)),0)+IFERROR(INDEX(Talenti!$E$5:$E$24,MATCH(G15,Talenti!$A$5:$A$24,0)),0)+IFERROR(INDEX(Talenti!$E$5:$E$24,MATCH(H15,Talenti!$A$5:$A$24,0)),0))) -> 7 | S15: =MAX(0,MIN(20,M15+IFERROR(INDEX(Talenti!$F$5:$F$24,MATCH(F15,Talenti!$A$5:$A$24,0)),0)+IFERROR(INDEX(Talenti!$F$5:$F$24,MATCH(G15,Talenti!$A$5:$A$24,0)),0)+IFERROR(INDEX(Talenti!$F$5:$F$24,MATCH(H15,Talenti!$A$5:$A$24,0)),0))) -> 15 | T15: =MAX(0,MIN(20,N15+IFERROR(INDEX(Talenti!$G$5:$G$24,MATCH(F15,Talenti!$A$5:$A$24,0)),0)+IFERROR(INDEX(Talenti!$G$5:$G$24,MATCH(G15,Talenti!$A$5:$A$24,0)),0)+IFERROR(INDEX(Talenti!$G$5:$G$24,MATCH(H15,Talenti!$A$5:$A$24,0)),0))) -> 13 | U15: =50+IFERROR(INDEX(Talenti!$H$5:$H$24,MATCH(F15,Talenti!$A$5:$A$24,0)),0)+IFERROR(INDEX(Talenti!$H$5:$H$24,MATCH(G15,Talenti!$A$5:$A$24,0)),0)+IFERROR(INDEX(Talenti!$H$5:$H$24,MATCH(H15,Talenti!$A$5:$A$24,0)),0) -> 70 | V15: Arrivato da Amburgo per "razionalizzare il mercato italiano". Trova la pausa caffè una perdita di efficienza.
A16: Ambrogio Brambilla | B16: 79 | C16: CEO concorrente | D16: Fondatore di F.lli Brambilla | E16: Milano | F16: Dialetto stretto | G16: Braccino corto | I16: 12 | J16: 9 | K16: 10 | L16: 13 | M16: 11 | N16: 3 | O16: =MAX(0,MIN(20,I16+IFERROR(INDEX(Talenti!$B$5:$B$24,MATCH(F16,Talenti!$A$5:$A$24,0)),0)+IFERROR(INDEX(Talenti!$B$5:$B$24,MATCH(G16,Talenti!$A$5:$A$24,0)),0)+IFERROR(INDEX(Talenti!$B$5:$B$24,MATCH(H16,Talenti!$A$5:$A$24,0)),0))) -> 12 | P16: =MAX(0,MIN(20,J16+IFERROR(INDEX(Talenti!$C$5:$C$24,MATCH(F16,Talenti!$A$5:$A$24,0)),0)+IFERROR(INDEX(Talenti!$C$5:$C$24,MATCH(G16,Talenti!$A$5:$A$24,0)),0)+IFERROR(INDEX(Talenti!$C$5:$C$24,MATCH(H16,Talenti!$A$5:$A$24,0)),0))) -> 9 | Q16: =MAX(0,MIN(20,K16+IFERROR(INDEX(Talenti!$D$5:$D$24,MATCH(F16,Talenti!$A$5:$A$24,0)),0)+IFERROR(INDEX(Talenti!$D$5:$D$24,MATCH(G16,Talenti!$A$5:$A$24,0)),0)+IFERROR(INDEX(Talenti!$D$5:$D$24,MATCH(H16,Talenti!$A$5:$A$24,0)),0))) -> 8 | R16: =MAX(0,MIN(20,L16+IFERROR(INDEX(Talenti!$E$5:$E$24,MATCH(F16,Talenti!$A$5:$A$24,0)),0)+IFERROR(INDEX(Talenti!$E$5:$E$24,MATCH(G16,Talenti!$A$5:$A$24,0)),0)+IFERROR(INDEX(Talenti!$E$5:$E$24,MATCH(H16,Talenti!$A$5:$A$24,0)),0))) -> 13 | S16: =MAX(0,MIN(20,M16+IFERROR(INDEX(Talenti!$F$5:$F$24,MATCH(F16,Talenti!$A$5:$A$24,0)),0)+IFERROR(INDEX(Talenti!$F$5:$F$24,MATCH(G16,Talenti!$A$5:$A$24,0)),0)+IFERROR(INDEX(Talenti!$F$5:$F$24,MATCH(H16,Talenti!$A$5:$A$24,0)),0))) -> 14 | T16: =MAX(0,MIN(20,N16+IFERROR(INDEX(Talenti!$G$5:$G$24,MATCH(F16,Talenti!$A$5:$A$24,0)),0)+IFERROR(INDEX(Talenti!$G$5:$G$24,MATCH(G16,Talenti!$A$5:$A$24,0)),0)+IFERROR(INDEX(Talenti!$G$5:$G$24,MATCH(H16,Talenti!$A$5:$A$24,0)),0))) -> 3 | U16: =50+IFERROR(INDEX(Talenti!$H$5:$H$24,MATCH(F16,Talenti!$A$5:$A$24,0)),0)+IFERROR(INDEX(Talenti!$H$5:$H$24,MATCH(G16,Talenti!$A$5:$A$24,0)),0)+IFERROR(INDEX(Talenti!$H$5:$H$24,MATCH(H16,Talenti!$A$5:$A$24,0)),0) -> 50 | V16: Fondò l'azienda nel 1958 con un camion e un mulo. Non ha ancora deciso a quale dei tre figli lasciarla, e i figli non si parlano.
A17: Renato Bartolazzi | B17: 63 | C17: CEO concorrente | D17: CEO del Gruppo Bartolazzi | E17: Fuori mappa | F17: Conosce tutti al bar | G17: Ha fatto il militare | I17: 14 | J17: 10 | K17: 11 | L17: 12 | M17: 10 | N17: 7 | O17: =MAX(0,MIN(20,I17+IFERROR(INDEX(Talenti!$B$5:$B$24,MATCH(F17,Talenti!$A$5:$A$24,0)),0)+IFERROR(INDEX(Talenti!$B$5:$B$24,MATCH(G17,Talenti!$A$5:$A$24,0)),0)+IFERROR(INDEX(Talenti!$B$5:$B$24,MATCH(H17,Talenti!$A$5:$A$24,0)),0))) -> 14 | P17: =MAX(0,MIN(20,J17+IFERROR(INDEX(Talenti!$C$5:$C$24,MATCH(F17,Talenti!$A$5:$A$24,0)),0)+IFERROR(INDEX(Talenti!$C$5:$C$24,MATCH(G17,Talenti!$A$5:$A$24,0)),0)+IFERROR(INDEX(Talenti!$C$5:$C$24,MATCH(H17,Talenti!$A$5:$A$24,0)),0))) -> 11 | Q17: =MAX(0,MIN(20,K17+IFERROR(INDEX(Talenti!$D$5:$D$24,MATCH(F17,Talenti!$A$5:$A$24,0)),0)+IFERROR(INDEX(Talenti!$D$5:$D$24,MATCH(G17,Talenti!$A$5:$A$24,0)),0)+IFERROR(INDEX(Talenti!$D$5:$D$24,MATCH(H17,Talenti!$A$5:$A$24,0)),0))) -> 12 | R17: =MAX(0,MIN(20,L17+IFERROR(INDEX(Talenti!$E$5:$E$24,MATCH(F17,Talenti!$A$5:$A$24,0)),0)+IFERROR(INDEX(Talenti!$E$5:$E$24,MATCH(G17,Talenti!$A$5:$A$24,0)),0)+IFERROR(INDEX(Talenti!$E$5:$E$24,MATCH(H17,Talenti!$A$5:$A$24,0)),0))) -> 17 | S17: =MAX(0,MIN(20,M17+IFERROR(INDEX(Talenti!$F$5:$F$24,MATCH(F17,Talenti!$A$5:$A$24,0)),0)+IFERROR(INDEX(Talenti!$F$5:$F$24,MATCH(G17,Talenti!$A$5:$A$24,0)),0)+IFERROR(INDEX(Talenti!$F$5:$F$24,MATCH(H17,Talenti!$A$5:$A$24,0)),0))) -> 10 | T17: =MAX(0,MIN(20,N17+IFERROR(INDEX(Talenti!$G$5:$G$24,MATCH(F17,Talenti!$A$5:$A$24,0)),0)+IFERROR(INDEX(Talenti!$G$5:$G$24,MATCH(G17,Talenti!$A$5:$A$24,0)),0)+IFERROR(INDEX(Talenti!$G$5:$G$24,MATCH(H17,Talenti!$A$5:$A$24,0)),0))) -> 7 | U17: =50+IFERROR(INDEX(Talenti!$H$5:$H$24,MATCH(F17,Talenti!$A$5:$A$24,0)),0)+IFERROR(INDEX(Talenti!$H$5:$H$24,MATCH(G17,Talenti!$A$5:$A$24,0)),0)+IFERROR(INDEX(Talenti!$H$5:$H$24,MATCH(H17,Talenti!$A$5:$A$24,0)),0) -> 55 | V17: Guida da Bologna una rete di corrieri in tutta Italia. Nel Nord-Ovest difende ogni cliente come se fosse l'ultimo.
A18: Denis Fatica | B18: 45 | C18: CEO concorrente | D18: Presidente della Cooperativa La Fatica | E18: Pavia | F18: Braccino corto | G18: Conosce tutti al bar | I18: 10 | J18: 6 | K18: 11 | L18: 7 | M18: 12 | N18: 5 | O18: =MAX(0,MIN(20,I18+IFERROR(INDEX(Talenti!$B$5:$B$24,MATCH(F18,Talenti!$A$5:$A$24,0)),0)+IFERROR(INDEX(Talenti!$B$5:$B$24,MATCH(G18,Talenti!$A$5:$A$24,0)),0)+IFERROR(INDEX(Talenti!$B$5:$B$24,MATCH(H18,Talenti!$A$5:$A$24,0)),0))) -> 10 | P18: =MAX(0,MIN(20,J18+IFERROR(INDEX(Talenti!$C$5:$C$24,MATCH(F18,Talenti!$A$5:$A$24,0)),0)+IFERROR(INDEX(Talenti!$C$5:$C$24,MATCH(G18,Talenti!$A$5:$A$24,0)),0)+IFERROR(INDEX(Talenti!$C$5:$C$24,MATCH(H18,Talenti!$A$5:$A$24,0)),0))) -> 6 | Q18: =MAX(0,MIN(20,K18+IFERROR(INDEX(Talenti!$D$5:$D$24,MATCH(F18,Talenti!$A$5:$A$24,0)),0)+IFERROR(INDEX(Talenti!$D$5:$D$24,MATCH(G18,Talenti!$A$5:$A$24,0)),0)+IFERROR(INDEX(Talenti!$D$5:$D$24,MATCH(H18,Talenti!$A$5:$A$24,0)),0))) -> 12 | R18: =MAX(0,MIN(20,L18+IFERROR(INDEX(Talenti!$E$5:$E$24,MATCH(F18,Talenti!$A$5:$A$24,0)),0)+IFERROR(INDEX(Talenti!$E$5:$E$24,MATCH(G18,Talenti!$A$5:$A$24,0)),0)+IFERROR(INDEX(Talenti!$E$5:$E$24,MATCH(H18,Talenti!$A$5:$A$24,0)),0))) -> 7 | S18: =MAX(0,MIN(20,M18+IFERROR(INDEX(Talenti!$F$5:$F$24,MATCH(F18,Talenti!$A$5:$A$24,0)),0)+IFERROR(INDEX(Talenti!$F$5:$F$24,MATCH(G18,Talenti!$A$5:$A$24,0)),0)+IFERROR(INDEX(Talenti!$F$5:$F$24,MATCH(H18,Talenti!$A$5:$A$24,0)),0))) -> 15 | T18: =MAX(0,MIN(20,N18+IFERROR(INDEX(Talenti!$G$5:$G$24,MATCH(F18,Talenti!$A$5:$A$24,0)),0)+IFERROR(INDEX(Talenti!$G$5:$G$24,MATCH(G18,Talenti!$A$5:$A$24,0)),0)+IFERROR(INDEX(Talenti!$G$5:$G$24,MATCH(H18,Talenti!$A$5:$A$24,0)),0))) -> 5 | U18: =50+IFERROR(INDEX(Talenti!$H$5:$H$24,MATCH(F18,Talenti!$A$5:$A$24,0)),0)+IFERROR(INDEX(Talenti!$H$5:$H$24,MATCH(G18,Talenti!$A$5:$A$24,0)),0)+IFERROR(INDEX(Talenti!$H$5:$H$24,MATCH(H18,Talenti!$A$5:$A$24,0)),0) -> 50 | V18: Vince le gare con i prezzi più bassi della regione. Come ci riesca è oggetto di tre indagini e di molte chiacchiere.
A19: Ludovica Sprint | B19: 27 | C19: CEO concorrente | D19: Fondatrice di Spedisci.io (dal 2012) | E19: Milano | F19: Parla con i robot | G19: Sempre al telefono | H19: Insonne | I19: 7 | J19: 8 | K19: 13 | L19: 9 | M19: 6 | N19: 16 | O19: =MAX(0,MIN(20,I19+IFERROR(INDEX(Talenti!$B$5:$B$24,MATCH(F19,Talenti!$A$5:$A$24,0)),0)+IFERROR(INDEX(Talenti!$B$5:$B$24,MATCH(G19,Talenti!$A$5:$A$24,0)),0)+IFERROR(INDEX(Talenti!$B$5:$B$24,MATCH(H19,Talenti!$A$5:$A$24,0)),0))) -> 5 | P19: =MAX(0,MIN(20,J19+IFERROR(INDEX(Talenti!$C$5:$C$24,MATCH(F19,Talenti!$A$5:$A$24,0)),0)+IFERROR(INDEX(Talenti!$C$5:$C$24,MATCH(G19,Talenti!$A$5:$A$24,0)),0)+IFERROR(INDEX(Talenti!$C$5:$C$24,MATCH(H19,Talenti!$A$5:$A$24,0)),0))) -> 5 | Q19: =MAX(0,MIN(20,K19+IFERROR(INDEX(Talenti!$D$5:$D$24,MATCH(F19,Talenti!$A$5:$A$24,0)),0)+IFERROR(INDEX(Talenti!$D$5:$D$24,MATCH(G19,Talenti!$A$5:$A$24,0)),0)+IFERROR(INDEX(Talenti!$D$5:$D$24,MATCH(H19,Talenti!$A$5:$A$24,0)),0))) -> 15 | R19: =MAX(0,MIN(20,L19+IFERROR(INDEX(Talenti!$E$5:$E$24,MATCH(F19,Talenti!$A$5:$A$24,0)),0)+IFERROR(INDEX(Talenti!$E$5:$E$24,MATCH(G19,Talenti!$A$5:$A$24,0)),0)+IFERROR(INDEX(Talenti!$E$5:$E$24,MATCH(H19,Talenti!$A$5:$A$24,0)),0))) -> 7 | S19: =MAX(0,MIN(20,M19+IFERROR(INDEX(Talenti!$F$5:$F$24,MATCH(F19,Talenti!$A$5:$A$24,0)),0)+IFERROR(INDEX(Talenti!$F$5:$F$24,MATCH(G19,Talenti!$A$5:$A$24,0)),0)+IFERROR(INDEX(Talenti!$F$5:$F$24,MATCH(H19,Talenti!$A$5:$A$24,0)),0))) -> 6 | T19: =MAX(0,MIN(20,N19+IFERROR(INDEX(Talenti!$G$5:$G$24,MATCH(F19,Talenti!$A$5:$A$24,0)),0)+IFERROR(INDEX(Talenti!$G$5:$G$24,MATCH(G19,Talenti!$A$5:$A$24,0)),0)+IFERROR(INDEX(Talenti!$G$5:$G$24,MATCH(H19,Talenti!$A$5:$A$24,0)),0))) -> 19 | U19: =50+IFERROR(INDEX(Talenti!$H$5:$H$24,MATCH(F19,Talenti!$A$5:$A$24,0)),0)+IFERROR(INDEX(Talenti!$H$5:$H$24,MATCH(G19,Talenti!$A$5:$A$24,0)),0)+IFERROR(INDEX(Talenti!$H$5:$H$24,MATCH(H19,Talenti!$A$5:$A$24,0)),0) -> 35 | V19: Ha raccolto 20 milioni dagli investitori con una presentazione di 12 slide. Promette consegne in due ore e un'app per tutto.

Sheet Talenti
A1: Talenti
A2: Modificatori sulle sei abilità (scala 0-20) e sulla tenuta allo stress. Celle in blu: da bilanciare.
A4: Talento | B4: Operazioni | C4: Precisione | D4: Negoziazione | E4: Leadership | F4: Amministrazione | G4: Innovazione | H4: Tenuta allo stress | I4: Tipo | J4: Altri effetti
A5: Un milione di km al volante | B5: 4 | C5: 0 | D5: 0 | E5: 1 | F5: 0 | G5: -2 | H5: 0 | I5: Origine | J5: Gli autisti lo rispettano: morale autisti +5
A6: Allergico al gestionale | B6: 0 | C6: 0 | D6: 0 | E6: 0 | F6: 0 | G6: -4 | H6: 0 | I6: Negativo | J6: Curva di apprendimento +50% nel suo magazzino
A7: Dialetto stretto | B7: 0 | C7: 0 | D7: -2 | E7: 2 | F7: 0 | G7: 0 | H7: 0 | I7: Misto | J7: Opinione degli operai +10, dei clienti multinazionali −10
A8: Laureato in Bocconi | B8: -1 | C8: 0 | D8: 1 | E8: 0 | F8: 3 | G8: 0 | H8: 0 | I8: Origine | J8: Accesso a eventi con banche e investitori
A9: Papà ha sempre ragione | B9: 0 | C9: 0 | D9: 0 | E9: -2 | F9: 0 | G9: 0 | H9: -5 | I9: Negativo | J9: Il fondatore interviene negli eventi
A10: Sempre al telefono | B10: 0 | C10: -1 | D10: 2 | E10: 0 | F10: 0 | G10: 0 | H10: -5 | I10: Misto | J10: Risponde ai clienti anche in ferie
A11: Parla per acronimi | B11: 0 | C11: 0 | D11: 2 | E11: -3 | F11: 0 | G11: 0 | H11: 0 | I11: Misto | J11: Bonus nelle gare dei clienti grandi
A12: Stacanovista | B12: 2 | C12: 0 | D12: 0 | E12: 0 | F12: 0 | G12: 0 | H12: -15 | I12: Misto | J12: Lo stress sale il doppio
A13: Cena col buyer | B13: 0 | C13: 0 | D13: 4 | E13: 0 | F13: 0 | G13: 0 | H13: -10 | I13: Positivo | J13: Scelte speciali negli eventi con i clienti
A14: Excel-dipendente | B14: 0 | C14: 3 | D14: 0 | E14: -2 | F14: 2 | G14: 0 | H14: 0 | I14: Misto | J14: Report KPI più precisi
A15: Parla con i robot | B15: 0 | C15: 0 | D15: 0 | E15: -2 | F15: 0 | G15: 3 | H15: 0 | I15: Misto | J15: Curva di apprendimento −30%
A16: Calma olimpica | B16: 0 | C16: 0 | D16: 0 | E16: 1 | F16: 0 | G16: 0 | H16: 20 | I16: Positivo | J16: Ignora gli eventi di panico
... A24: Tifo sfegatato | B24: 0 | C24: 0 | D24: 0 | E24: 1 | F24: 0 | G24: 0 | H24: 0 | I24: Misto | J24: Eventi speciali nei giorni del derby

Sheet Recruiting
A1: Recruiting: compensi, welfare, canali e credibilità
A2: Valori di partenza indicativi per il 2002, da bilanciare. Celle in blu su sfondo giallo: da modificare. Il resto sono formule.
A4: 1. Ruoli e stipendio di mercato (RAL di riferimento, anno 2002)
A5: Ruolo | B5: RAL di mercato (€) | C5: Costo azienda (€/anno) | D5: Disponibilità candidati (1-5) | E5: Statistica principale | F5: Note | H5: Coefficiente costo azienda
A6: Autista patente CE | B6: 23000 | C6: =B6*$H$6 -> 32660 | D6: 2 | E6: Operazioni | F6: Carenza cronica: pochi candidati, molto contesi | H6: 1.42
A7: Autista patente C (furgoni/motrici) | B7: 20000 | C7: =B7*$H$6 -> 28400 | D7: 3 | E7: Operazioni | H7: Ipotesi: contributi, TFR e oneri ≈ +42% sulla RAL
A8: Magazziniere / mulettista | B8: 18500 | C8: =B8*$H$6 -> 26270 | D8: 4 | E8: Operazioni | F8: Spesso fornito da cooperative
A9: Impiegato traffico / customer service | B9: 22000 | C9: =B9*$H$6 -> 31240 | D9: 3 | E9: Commerciale | F9: Pianifica i viaggi, parla con i clienti
A10: Capo turno magazzino | B10: 27000 | C10: =B10*$H$6 -> 38340 | D10: 3 | E10: Persone
A11: Manager di magazzino | B11: 48000 | C11: =B11*$H$6 -> 68160 | D11: 2 | E11: Operazioni/Persone | F11: Il "vassallo" che governa un magazzino
A12: Direttore (consiglio di sede) | B12: 75000 | C12: =B12*$H$6 -> 106500 | D12: 1 | E12: Dipende dal ruolo | F12: Solo tramite head hunter o promozione
A14: 2. Province del Nord-Ovest: coefficiente stipendi e bacino di candidati
A15: Provincia | B15: Coeff. stipendi | C15: Bacino candidati (1-5) | D15: Concorrenza (1-5) | E15: Polo logistico | F15: RAL autista CE in provincia (€)
A16: Milano | B16: 1.1 | C16: 5 | D16: 5 | E16: Milano Est, Pioltello | F16: =$B$6*B16 -> 25300
A17: Torino | B17: 1.03 | C17: 4 | D17: 4 | E17: Orbassano | F17: =$B$6*B17 -> 23690
A18: Genova | B18: 1.04 | C18: 3 | D18: 3 | E18: Porto, Voltri | F18: =$B$6*B18 -> 23920
A19: Bergamo | B19: 1.03 | C19: 4 | D19: 4 | E19: Orio al Serio | F19: =$B$6*B19 -> 23690
A20: Brescia | B20: 1.02 | C20: 4 | D20: 3 | E20: Brescia Est | F20: =$B$6*B20 -> 23460
A21: Novara | B21: 1 | C21: 3 | D21: 3 | E21: CIM Novara | F21: =$B$6*B21 -> 23000
A22: Lodi | B22: 1 | C22: 3 | D22: 4 | E22: Lodi, Casalpusterlengo | F22: =$B$6*B22 -> 23000
A23: Alessandria | B23: 0.97 | C23: 3 | D23: 2 | E23: Rivalta Scrivia | F23: =$B$6*B23 -> 22310
A24: Pavia | B24: 0.97 | C24: 2 | D24: 2 | E24: Mortara | F24: =$B$6*B24 -> 22310
A25: Aosta | B25: 1 | C25: 1 | D25: 1 | E25: Aosta | F25: =$B$6*B25 -> 23000
A27: 3. Voci di welfare
A28: Voce | B28: Costo per dipendente (€/mese) | C28: Punti attrattività | D28: Effetto sul morale | E28: Disponibile dal | F28: Note
A29: Buoni pasto | B29: 110 | C29: 6 | D29: +5 | E29: 2002
A30: Mensa aziendale | B30: 90 | C30: 5 | D30: +4 | E30: 2002 | F30: In più costo fisso di 1.500 €/mese per sito
A31: Assicurazione sanitaria integrativa | B31: 35 | C31: 7 | D31: +5 | E31: 2002
A32: Premio di produzione | B32: 80 | C32: 6 | D32: +6 | E32: 2002 | F32: Legato ai KPI del magazzino
A33: Orari flessibili | B33: 0 | C33: 5 | D33: +5 | E33: 2002 | F33: Costa 2% di produttività invece di denaro
A34: Formazione continua | B34: 25 | C34: 4 | D34: +3 | E34: 2002 | F34: Aumenta anche l'esperienza
A35: Navetta dalla stazione | B35: 20 | C35: 3 | D35: +2 | E35: 2002 | F35: Utile nei poli fuori città
A36: Asilo convenzionato | B36: 40 | C36: 4 | D36: +4 | E36: 2008
A37: Smart working (solo uffici) | B37: 0 | C37: 6 | D37: +6 | E37: 2020 | F37: Solo impiegati e manager
A39: 4. Canali di ricerca
A40: Canale | B40: Costo per assunzione (€) | C40: Tempo (giorni) | D40: Qualità media candidati (1-5) | E40: Ruoli | F40: Effetti collaterali
A41: Annuncio | B41: 300 | C41: 30 | D41: 2 | E41: Tutti tranne direttori | F41: Qualità molto variabile
A42: Agenzia interinale | B42: 1200 | C42: 7 | D42: 3 | E42: Autisti, magazzinieri, impiegati | F42: Contratto temporaneo, costo orario +15%
A43: Cooperativa | B43: 0 | C43: 5 | D43: 2 | E43: Magazzinieri | F43: Costo orario -10%, morale -10, rischio vertenze
A44: Passaparola | B44: 0 | C44: 20 | D44: 4 | E44: Tutti tranne direttori | F44: Funziona solo con morale aziendale sopra 60
A45: Head hunter | B45: 15000 | C45: 45 | D45: 5 | E45: Manager e direttori | F45: Porta personaggi con tratti rari
A47: 5. Credibilità aziendale (0-100, partenza 50)
A48: Evento | B48: Effetto sulla credibilità | C48: Note
A49: Stipendi pagati puntuali per 12 mesi | B49: 5
A50: Apertura di un nuovo magazzino | B50: 4 | C50: Segnale di crescita
A51: Premio o riconoscimento di settore | B51: 6
A52: Welfare migliore della media provinciale | B52: 3 | C52: Ogni anno
A53: Ritardo nel pagamento degli stipendi | B53: -12
A54: Licenziamenti collettivi | B54: -15 | C54: Dimezzato se ricollochi il personale
A55: Incidente grave sul lavoro | B55: -10
A56: Vertenza sindacale | B56: -6
A57: Recensione virale su LavoroBrutto.it | B57: -4 | C57: Evento parodistico
A59: 6. Calcolatore: un candidato accetta la nostra offerta?
A60: Ruolo | B60: Autista patente CE
A61: Provincia | B61: Milano
A62: Stipendio offerto (RAL €) | B62: 25000
A63: Voci di welfare attive: punti totali | B63: =SUM(C29:C31) -> 18 | C63: Esempio: buoni pasto + mensa + assicurazione. Cambia l'intervallo per provare altre combinazioni.
A64: Credibilità aziendale (0-100) | B64: 50
A65: Prospettive di crescita (0-10) | B65: 5
A66: Soglia del candidato (attrattività minima) | B66: 55
A67: RAL di mercato in provincia (€) | B67: =INDEX($B$6:$B$12,MATCH(B60,$A$6:$A$12,0))*INDEX($B$16:$B$25,MATCH(B61,$A$16:$A$25,0)) -> 25300
A68: Punti compenso | B68: =MAX(-30,MIN(30,(B62/B67-1)*200)) -> -2.3715415 | C68: Ogni 1% sopra il mercato = +2 punti (max ±30)
A69: Attrattività totale | B69: =30+B68+B63+(B64-50)*0.5+B65 -> 50.628458 | C69: Formula: 30 base + compenso + welfare + (credibilità − 50) × 0,5 + prospettive
A70: Probabilità che accetti | B70: =MAX(0,MIN(1,0.5+(B69-B66)/30)) -> 0.35428195 | C70: 50% se l'attrattività è pari alla soglia; ogni 3 punti in più o in meno = ±10%
A71: Costo azienda annuo dell'assunzione (€) | B71: =B62*$H$6+SUM(B29:B31)*12 -> 38320

Sheet Tecnologie
A1: Investimenti in tecnologia
A2: Ricerca una volta a livello aziendale, poi installazione in ogni magazzino. Effetti in punti percentuali sui KPI del magazzino. Valori di partenza da bilanciare.
A4: Parametri
A5: Innovazione del Direttore Tecnologia (0-10) | B5: 5
A6: Riduzione tempi di ricerca per punto di Innovazione | B6: 0.05
A7: Rimborso Bando Fabbrica 4.0 (dal 2017) | B7: 0.4
A8: Maggiorazione del leasing sul costo totale | B8: 0.18
A10: Ramo | B10: Tecnologia | C10: Anno di sblocco | D10: Prerequisito | E10: Costo ricerca (€) | F10: Mesi di ricerca (base) | G10: Mesi di ricerca effettivi | H10: Installazione per sito (€) | I10: Canone mensile per sito (€) | J10: Costo primo anno per sito (€) | K10: Effetto puntualità (pp) | L10: Effetto accuratezza (pp) | M10: Settimane di apprendimento | N10: Altri effetti
A11: Informatizzazione | B11: Gestionale di base | C11: 2002 | D11: — | E11: 15000 | F11: 2 | G11: =ROUND(F11*MAX(0.4,1-$B$5*$B$6),1) -> 1.5 | H11: 5000 | I11: 300 | J11: =H11*IF(C11>=2017,1-$B$7,1)+I11*12 -> 8600 | K11: 1 | L11: 1 | M11: 2
A12: Informatizzazione | B12: WMS di base | C12: 2002 | D12: Gestionale di base | E12: 40000 | F12: 4 | G12: =ROUND(F12*MAX(0.4,1-$B$5*$B$6),1) -> 3 | H12: 25000 | I12: 800 | J12: =H12*IF(C12>=2017,1-$B$7,1)+I12*12 -> 34600 | K12: 1 | L12: 3 | M12: 6 | N12: Errori di inventario dimezzati
A13: Informatizzazione | B13: EDI con i clienti | C13: 2003 | D13: Gestionale di base | E13: 30000 | F13: 3 | G13: =ROUND(F13*MAX(0.4,1-$B$5*$B$6),1) -> 2.3 | H13: 5000 | I13: 400 | J13: =H13*IF(C13>=2017,1-$B$7,1)+I13*12 -> 9800 | K13: 2 | L13: 1 | M13: 3 | N13: Richiesto da molti clienti della GDO
A14: Informatizzazione | B14: WMS avanzato multi-sito | C14: 2010 | D14: WMS di base | E14: 90000 | F14: 6 | G14: =ROUND(F14*MAX(0.4,1-$B$5*$B$6),1) -> 4.5 | H14: 40000 | I14: 1500 | J14: =H14*IF(C14>=2017,1-$B$7,1)+I14*12 -> 58000 | K14: 1 | L14: 3 | M14: 8 | N14: Sposta merce tra magazzini
A15: Magazzino | B15: Lettori barcode | C15: 2002 | D15: — | E15: 10000 | F15: 1 | G15: =ROUND(F15*MAX(0.4,1-$B$5*$B$6),1) -> 0.8 | H15: 12000 | I15: 150 | J15: =H15*IF(C15>=2017,1-$B$7,1)+I15*12 -> 13800 | K15: 0 | L15: 2 | M15: 2
A16: Magazzino | B16: Terminali in radiofrequenza | C16: 2004 | D16: Lettori barcode; WMS di base | E16: 25000 | F16: 3 | G16: =ROUND(F16*MAX(0.4,1-$B$5*$B$6),1) -> 2.3 | H16: 30000 | I16: 400 | J16: =H16*IF(C16>=2017,1-$B$7,1)+I16*12 -> 34800 | K16: 1 | L16: 2 | M16: 4
A17: Magazzino | B17: Pick-to-light | C17: 2008 | D17: Terminali in radiofrequenza | E17: 40000 | F17: 4 | G17: =ROUND(F17*MAX(0.4,1-$B$5*$B$6),1) -> 3 | H17: 80000 | I17: 600 | J17: =H17*IF(C17>=2017,1-$B$7,1)+I17*12 -> 87200 | K17: 1 | L17: 3 | M17: 4 | N17: Picking +15% più veloce
A18: Magazzino | B18: Magazzino verticale automatico | C18: 2012 | D18: WMS avanzato multi-sito | E18: 80000 | F18: 6 | G18: =ROUND(F18*MAX(0.4,1-$B$5*$B$6),1) -> 4.5 | H18: 400000 | I18: 2500 | J18: =H18*IF(C18>=2017,1-$B$7,1)+I18*12 -> 430000 | K18: 1 | L18: 2 | M18: 10 | N18: Capacità del sito +20%
A19: Magazzino | B19: Robot mobili (AMR) | C19: 2018 | D19: Magazzino verticale automatico | E19: 150000 | F19: 8 | G19: =ROUND(F19*MAX(0.4,1-$B$5*$B$6),1) -> 6 | H19: 600000 | I19: 4000 | J19: =H19*IF(C19>=2017,1-$B$7,1)+I19*12 -> 408000 | K19: 1 | L19: 2 | M19: 12 | N19: Magazzinieri necessari -30%; tensione sindacale
A20: Trasporto | B20: Telematica GPS | C20: 2004 | D20: — | E20: 20000 | F20: 2 | G20: =ROUND(F20*MAX(0.4,1-$B$5*$B$6),1) -> 1.5 | H20: 10000 | I20: 500 | J20: =H20*IF(C20>=2017,1-$B$7,1)+I20*12 -> 16000 | K20: 2 | L20: 0 | M20: 3 | N20: Mezzi visibili in tempo reale
A21: Trasporto | B21: Pianificazione delle rotte | C21: 2007 | D21: Telematica GPS | E21: 50000 | F21: 5 | G21: =ROUND(F21*MAX(0.4,1-$B$5*$B$6),1) -> 3.8 | H21: 15000 | I21: 600 | J21: =H21*IF(C21>=2017,1-$B$7,1)+I21*12 -> 22200 | K21: 3 | L21: 0 | M21: 6 | N21: Gasolio -5%
A22: Trasporto | B22: Mezzi a metano liquido (LNG) | C22: 2014 | D22: — | E22: 60000 | F22: 6 | G22: =ROUND(F22*MAX(0.4,1-$B$5*$B$6),1) -> 4.5 | H22: 50000 | I22: 300 | J22: =H22*IF(C22>=2017,1-$B$7,1)+I22*12 -> 53600 | K22: 0 | L22: 0 | M22: 2 | N22: Gasolio -20%, credibilità +3
A23: Trasporto | B23: Furgoni elettrici urbani | C23: 2020 | D23: Telematica GPS | E23: 80000 | F23: 6 | G23: =ROUND(F23*MAX(0.4,1-$B$5*$B$6),1) -> 4.5 | H23: 90000 | I23: 800 | J23: =H23*IF(C23>=2017,1-$B$7,1)+I23*12 -> 63600 | K23: 0 | L23: 0 | M23: 4 | N23: Accesso alle ZTL, credibilità +4
A24: Dati | B24: Cruscotto KPI | C24: 2006 | D24: Gestionale di base | E24: 20000 | F24: 2 | G24: =ROUND(F24*MAX(0.4,1-$B$5*$B$6),1) -> 1.5 | H24: 3000 | I24: 200 | J24: =H24*IF(C24>=2017,1-$B$7,1)+I24*12 -> 5400 | K24: 1 | L24: 1 | M24: 2 | N24: Avvisi anticipati sui clienti a rischio
A25: Dati | B25: Previsione dei volumi | C25: 2013 | D25: Cruscotto KPI; WMS avanzato multi-sito | E25: 70000 | F25: 6 | G25: =ROUND(F25*MAX(0.4,1-$B$5*$B$6),1) -> 4.5 | H25: 10000 | I25: 700 | J25: =H25*IF(C25>=2017,1-$B$7,1)+I25*12 -> 18400 | K25: 2 | L25: 1 | M25: 6 | N25: Meno straordinari nei picchi
A26: Dati | B26: Ottimizzazione con IA | C26: 2022 | D26: Previsione dei volumi; Pianificazione delle rotte | E26: 200000 | F26: 9 | G26: =ROUND(F26*MAX(0.4,1-$B$5*$B$6),1) -> 6.8 | H26: 30000 | I26: 2000 | J26: =H26*IF(C26>=2017,1-$B$7,1)+I26*12 -> 42000 | K26: 3 | L26: 2 | M26: 10
A27: Persone e sicurezza | B27: Formazione strutturata | C27: 2002 | D27: — | E27: 8000 | F27: 1 | G27: =ROUND(F27*MAX(0.4,1-$B$5*$B$6),1) -> 0.8 | H27: 4000 | I27: 250 | J27: =H27*IF(C27>=2017,1-$B$7,1)+I27*12 -> 7000 | K27: 0 | L27: 1 | M27: 1 | N27: Morale +3, incidenti -20%
A28: Persone e sicurezza | B28: Sistemi anti-collisione muletti | C28: 2010 | D28: Formazione strutturata | E28: 15000 | F28: 2 | G28: =ROUND(F28*MAX(0.4,1-$B$5*$B$6),1) -> 1.5 | H28: 25000 | I28: 150 | J28: =H28*IF(C28>=2017,1-$B$7,1)+I28*12 -> 26800 | K28: 0 | L28: 1 | M28: 2 | N28: Incidenti -40%
A29: Persone e sicurezza | B29: Esoscheletri | C29: 2019 | D29: Sistemi anti-collisione muletti | E29: 40000 | F29: 4 | G29: =ROUND(F29*MAX(0.4,1-$B$5*$B$6),1) -> 3 | H29: 35000 | I29: 300 | J29: =H29*IF(C29>=2017,1-$B$7,1)+I29*12 -> 24600 | K29: 0 | L29: 1 | M29: 4 | N29: Assenze per infortunio -25%, morale +3
A31: Note
A32: Durante le settimane di apprendimento il magazzino perde metà dell'effetto finale invece di guadagnarlo; formazione e morale alto le accorciano.
A33: Costo primo anno per sito = installazione (ridotta del rimborso del bando per le tecnologie dal 2017) + 12 canoni.
A34: Mesi di ricerca effettivi = mesi base × (1 − Innovazione × riduzione per punto), mai sotto il 40% del tempo base.
A35: Con il leasing l'installazione non si paga subito ma si spalma su 36 mesi, con la maggiorazione indicata nei parametri.
A37: Esempio leasing
A38: Tecnologia | B38: Pick-to-light
A39: Installazione per sito (€) | B39: =INDEX($H$11:$H$29,MATCH(B38,$B$11:$B$29,0)) -> 80000
A40: Rata mensile leasing su 36 mesi (€) | B40: =B39*(1+$B$8)/36 -> 2622.2222
A41: Totale rate + canone per mese (€) | B41: =B40+INDEX($I$11:$I$29,MATCH(B38,$B$11:$B$29,0)) -> 3222.2222

Sheet Eventi
A1: Catalogo eventi
A2: Ogni riga è un evento. Effetti indicativi da bilanciare. "Scelta speciale" compare solo se un personaggio ha il talento o l'abilità indicati. Tono: Ironico / Serio.
A4: ID | B4: Categoria | C4: Fonte | D4: Titolo | E4: Testo | F4: Quando può accadere | G4: Dal | H4: Al | I4: Frequenza | J4: Scelta A | K4: Effetti A | L4: Scelta B | M4: Effetti B | N4: Scelta speciale | O4: Requisito | P4: Effetti speciale | Q4: Tono | R4: Evento successivo
A5: MET-01 | B5: Meteo e strade | C5: Radio Traffico Nord-Ovest | D5: Nebbia in Val Padana | E5: Visibilità sotto i 50 metri da Pavia a Brescia. Gli autisti chiedono di rallentare. | F5: Ottobre–febbraio; magazzino in Lombardia o Piemonte | G5: 2002 | H5: 2040 | I5: Comune | J5: Rallenta tutto | K5: Puntualità −6 pp per 7 giorni in Lombardia e Piemonte | L5: Si viaggia lo stesso | M5: Puntualità −2 pp; 15% di rischio incidente (−10 credibilità, mezzo fermo 30 giorni) | N5: "Conosco ogni curva" | O5: Talento: Un milione di km al volante | P5: Puntualità −1 pp, nessun rischio | Q5: Ironico
A6: MET-02 | B6: Meteo e strade | C6: Radio Traffico Nord-Ovest | D6: Neve al Traforo del Frejus | E6: Il traforo chiude per neve. Le consegne per Lione e Parigi sono ferme. | F6: Dicembre–marzo; flussi verso la Francia | G6: 2002 | H6: 2040 | I6: Comune | J6: Devia dal Monte Bianco | K6: +450 € per viaggio, puntualità −3 pp sui flussi esteri | L6: Aspetta la riapertura | M6: Puntualità −12 pp sui flussi esteri per 3 giorni | N6: Prenota il treno (autostrada ferroviaria) | O6: Innovazione ≥ 12 | P6: +200 € per viaggio, puntualità invariata | Q6: Ironico
A7: MET-03 | B7: Meteo e strade | C7: Radio Traffico Nord-Ovest | D7: Allerta rossa in Liguria | E7: Piogge fortissime: A10 e A6 a rischio chiusura, la Protezione Civile invita a non circolare. | F7: Settembre–novembre; magazzino in provincia di Genova | G7: 2002 | H7: 2040 | I7: Rara | J7: Chiudi il magazzino di Genova per 2 giorni | K7: Ricavi −2 giorni, morale +5, nessun rischio | L7: Resta aperto | M7: 30% di rischio danni al magazzino (−40.000 €) e infortuni (−8 credibilità) | Q7: Serio | R7: MET-03b Raccolta fondi per i comuni colpiti
A8: MET-04 | B8: Meteo e strade | C8: Radio Traffico Nord-Ovest | D8: Afa record | E8: 40 °C a Milano. I gruppi frigo vanno in crisi e in magazzino si respira a fatica. | F8: Luglio–agosto | G8: 2002 | H8: 2040 | I8: Comune | J8: Compra ventilatori e acqua per tutti | K8: −3.000 €, morale +5 | L8: Turni anticipati all'alba | M8: Produttività −5% per 10 giorni, morale invariato | N8: Pausa gelato offerta dal CEO | O8: Talento: Cena col buyer | P8: −800 €, morale +8, stress CEO −5 | Q8: Ironico
A9: MET-05 | B9: Meteo e strade | C9: La Gazzetta del Muletto | D9: Mucche sulla statale | E9: In Valle d'Aosta una mandria blocca un camion per tre ore. L'autista posta la foto: 40.000 condivisioni. | F9: Maggio–settembre; flussi verso Aosta | G9: 2002 | H9: 2040 | I9: Rara | J9: Pubblica la foto sui canali aziendali | K9: Reputazione +3 | L9: Lascia perdere | M9: Nessun effetto | Q9: Ironico
A10: POL-01 | B10: Politica e burocrazia | C10: Il Mattinale del Ministero | D10: ZTL "Zero Camion" | E10: Il nuovo assessore vieta i furgoni sotto Euro 4 nel centro di Milano dal mese prossimo. | F10: Dal 2008; flussi verso Milano città | G10: 2008 | H10: 2040 | I10: Comune | J10: Rinnova i furgoni | K10: Costo dei nuovi mezzi; credibilità +3 | L10: Ricorso al TAR | M10: −5.000 € di avvocati; 40% di vincere e rinviare il divieto di 1 anno | N10: Una telefonata in Comune | O10: Amministrazione ≥ 14 | P10: Proroga di 6 mesi, ma l'assessore si ricorderà di te | Q10: Ironico | R10: POL-01b L'assessore chiede un favore
A11: POL-02 | B11: Politica e burocrazia | C11: Il Mattinale del Ministero | D11: Decreto Semplificazione | E11: Un decreto di 340 pagine semplifica le pratiche di trasporto. Nessuno ha capito cosa cambi. | F11: Una volta ogni 2-3 anni | G11: 2002 | H11: 2040 | I11: Comune | J11: Studiatelo con calma | K11: Amministrazione rallentata per 30 giorni (costi +3%) | L11: Assumi un consulente | M11: −6.000 €, nessun rallentamento | N11: "L'ho già letto stanotte" | O11: Talento: Excel-dipendente | P11: Nessun rallentamento, stress CEO +5 | Q11: Ironico
A12: POL-03 | B12: Politica e burocrazia | C12: Il Sole 24 Pallet | D12: Sciopero nazionale degli autotrasportatori | E12: Le associazioni di categoria fermano i camion per 5 giorni contro il caro gasolio. | F12: Prezzo del gasolio in forte aumento | G12: 2002 | H12: 2040 | I12: Rara | J12: Aderisci | K12: Puntualità −20 pp per 5 giorni, morale +10, credibilità +3 | L12: Lavora lo stesso | M12: Morale −8; 25% di blocchi ai caselli (mezzi fermi 2 giorni) | N12: Media tra sindacati e clienti | O12: Leadership ≥ 14 | P12: Puntualità −8 pp, morale +5 | Q12: Ironico
A13: POL-04 | B13: Politica e burocrazia | C13: Il Mattinale del Ministero | D13: Bando Fabbrica 4.0 | E13: Il bando rimborsa il 40% degli investimenti in tecnologia. La domanda è di 60 pagine. | F13: Dal 2017, una volta l'anno | G13: 2017 | H13: 2040 | I13: Comune | J13: Partecipa | K13: 3 impiegati occupati per 30 giorni; rimborso dopo 6-18 mesi | L13: Lascia perdere | M13: Nessun effetto | N13: Delegalo al Direttore Finanza | O13: Amministrazione ≥ 12 del Direttore Finanza | P13: Nessun impiegato occupato | Q13: Ironico | R13: POL-04b Il rimborso arriva (forse)
A14: POL-05 | B14: Politica e burocrazia | C14: La Gazzetta del Muletto | D14: Elezioni comunali | E14: Entrambi i candidati sindaci ti chiedono un contributo per la campagna. | F14: Ogni 5 anni nelle province con un tuo magazzino | G14: 2002 | H14: 2040 | I14: Comune | J14: Sostieni il candidato A | K14: −5.000 €; se vince, permessi più rapidi; se perde, controlli più frequenti | L14: Resta neutrale | M14: Nessun effetto | N14: Sostieni entrambi | O14: Negoziazione ≥ 15 | P14: −10.000 €, amico di chiunque vinca, 20% di scandalo (−8 reputazione) | Q14: Ironico
A15: POL-06 | B15: Politica e burocrazia | C15: Il Mattinale del Ministero | D15: Controllo dell'Ispettorato del Lavoro | E15: Gli ispettori si presentano alle 7:00 in magazzino. | F15: Più probabile se usi cooperative | G15: 2002 | H15: 2040 | I15: Comune | J15: Collabora | K15: Multa in base alle irregolarità (0-30.000 €) | L15: Chiedi un rinvio | M15: Multa +20%, credibilità −3 | N15: "Abbiamo tutto in ordine" | O15: Precisione ≥ 14 del manager del magazzino | P15: Nessuna multa, credibilità +2 | Q15: Ironico
A16: LOC-01 | B16: Vita locale | C16: Il Sole 24 Pallet | D16: Settimana della Moda | E16: A Milano arrivano buyer da tutto il mondo. I clienti della moda raddoppiano gli ordini. | F16: Febbraio e settembre; clienti del settore moda | G16: 2002 | H16: 2040 | I16: Comune | J16: Straordinari per tutti | K16: Ricavi moda ×2 per 10 giorni, morale −5 | L16: Usa i vettori esterni | M16: Ricavi moda ×2, margine −30% | Q16: Ironico
A17: LOC-02 | B17: Vita locale | C17: Radio Traffico Nord-Ovest | D17: Passa il Giro d'Italia | E17: Una tappa blocca due province per un giorno intero. | F17: Maggio | G17: 2002 | H17: 2040 | I17: Comune | J17: Sponsorizza la tappa | K17: −15.000 €, reputazione +6 | L17: Riorganizza le consegne | M17: Puntualità −5 pp per 1 giorno | Q17: Ironico
A18: LOC-03 | B18: Vita locale | C18: La Gazzetta del Muletto | D18: Derby della Mole | E18: Metà dei magazzinieri di Torino chiede il pomeriggio libero per la partita. | F18: Magazzino in provincia di Torino | G18: 2002 | H18: 2040 | I18: Comune | J18: Concedi il pomeriggio | K18: Produttività −40% per mezza giornata, morale +6 | L18: Nega il permesso | M18: Morale −8; 30% di malattie improvvise | N18: Megaschermo in magazzino | O18: Leadership ≥ 12 | P18: −1.500 €, morale +10, produttività −10% per mezza giornata | Q18: Ironico
A19: LOC-04 | B19: Vita locale | C19: La Gazzetta del Muletto | D19: Il prete benedice i camion | E19: Il parroco propone la benedizione annuale della flotta. | F19: Magazzini fuori dalle grandi città | G19: 2002 | H19: 2040 | I19: Rara | J19: Accetta e fai una donazione | K19: −500 €, morale +4, un autista ritira le dimissioni | L19: Rifiuta gentilmente | M19: Morale −2 tra gli autisti più anziani | Q19: Ironico
A20: LOC-05 | B20: Vita locale | C20: Il Sole 24 Pallet | D20: Olimpiadi invernali di Torino | E20: Torino ospita le Olimpiadi: servono trasporti per impianti, atleti e merci. | F20: Gennaio 2006 | G20: 2006 | H20: 2006 | I20: Datato | J20: Partecipa alla gara dei trasporti olimpici | K20: Gara speciale: contratto di 2 mesi molto redditizio | L20: Ignora | M20: Traffico +20% in provincia di Torino per 2 mesi | Q20: Ironico
A21: LOC-06 | B21: Vita locale | C21: Il Sole 24 Pallet | D21: Expo Milano | E21: Sei mesi di esposizione universale: i cantieri e poi i padiglioni chiedono logistica. | F21: 2014–2015 | G21: 2014 | H21: 2015 | I21: Datato | J21: Apri un presidio vicino a Rho | K21: Nuovo cliente temporaneo, reputazione +5 | L21: Ignora | M21: Domanda in provincia di Milano +10% per 6 mesi | Q21: Ironico
A22: PER-01 | B22: Personale | C22: La Gazzetta del Muletto | D22: Vincita al Superenalotto | E22: Un magazziniere vince 2 milioni e si licenzia sul gruppo WhatsApp aziendale. | F22: Qualsiasi momento | G22: 2002 | H22: 2040 | I22: Rara | J22: Fagli gli auguri | K22: Perdi un magazziniere esperto, morale +3 | L22: Chiedigli un investimento | M22: 30% di ottenere 100.000 € di prestito a tasso zero | Q22: Ironico
A23: PER-02 | B23: Personale | C23: La Gazzetta del Muletto | D23: Il cane del manager | E23: Il manager di Novara porta in ufficio il suo bassotto, Ragù. | F23: Qualsiasi magazzino | G23: 2002 | H23: 2040 | I23: Rara | J23: Permettilo | K23: Morale +5; 20% che qualcuno sia allergico (−3 morale amministrazione) | L23: Vietalo | M23: Opinione del manager −15 | Q23: Ironico
A24: PER-03 | B24: Personale | C24: La Gazzetta del Muletto | D24: Cena di Natale finita male | E24: Il Direttore Commerciale e il capo traffico hanno litigato sul karaoke. | F24: Dicembre | G24: 2002 | H24: 2040 | I24: Comune | J24: Organizza un chiarimento | K24: Stress CEO +3, rapporto ristabilito | L24: Lascia che si arrangino | M24: Puntualità −2 pp per 2 mesi | N24: Brindisi di riconciliazione | O24: Talento: Cena col buyer | P24: Opinione di entrambi verso il CEO +10 | Q24: Ironico
A25: PER-04 | B25: Personale | C25: La Gazzetta del Muletto | D25: L'autista influencer | E25: Un tuo autista ha 300.000 follower su TikTok con i video dalla cabina. | F25: Dal 2020 | G25: 2020 | H25: 2040 | I25: Rara | J25: Fallo testimonial | K25: Reputazione +6; 20% di video imbarazzante (−5) | L25: Chiedigli di smettere | M25: Opinione dell'autista −20, 40% che si licenzi | Q25: Ironico
A26: PER-05 | B26: Personale | C26: La Gazzetta del Muletto | D26: Furto di gasolio | E26: Di notte qualcuno ha svuotato tre serbatoi nel piazzale. | F26: Magazzini senza sorveglianza | G26: 2002 | H26: 2040 | I26: Comune | J26: Installa telecamere | K26: −8.000 €, furti futuri −80% | L26: Fidati del guardiano (74 anni) | M26: Altri furti possibili, morale +2 | Q26: Ironico
A27: PER-06 | B27: Personale | C27: La Gazzetta del Muletto | D27: Il gestionale si aggiorna da solo | E27: Venerdì sera il gestionale ha installato un aggiornamento. Lunedì nessuno stampa le bolle. | F27: Gestionale installato | G27: 2002 | H27: 2040 | I27: Comune | J27: Chiama l'assistenza | K27: Accuratezza −4 pp per 2 giorni, −1.200 € | L27: Torna alle bolle a mano | M27: Accuratezza −8 pp per 2 giorni | N27: "Lo sistemo io" | O27: Innovazione ≥ 14 | P27: Nessun effetto, stress +3 | Q27: Ironico
A28: CLI-01 | B28: Clienti e mercato | C28: Il Sole 24 Pallet | D28: Cambio di buyer | E28: Esselonga ha un nuovo buyer: vuole rinegoziare tutto e adora i report in PowerPoint. | F28: Clienti della GDO | G28: 2002 | H28: 2040 | I28: Comune | J28: Accetta la rinegoziazione | K28: Tariffa −4%, soddisfazione +10 | L28: Difendi le condizioni | M28: 30% di disdetta anticipata | N28: Presentazione da 80 slide | O28: Talento: Parla per acronimi | P28: Tariffa invariata, soddisfazione +5 | Q28: Ironico
A29: CLI-02 | B29: Clienti e mercato | C29: Il Sole 24 Pallet | D29: Black Friday | E29: Gli ordini dei clienti dell'elettronica triplicano per una settimana. | F29: Fine novembre, dal 2015 | G29: 2015 | H29: 2040 | I29: Comune | J29: Straordinari | K29: Ricavi ×3, morale −8, accuratezza −3 pp | L29: Assumi interinali | M29: −6.000 €, accuratezza −5 pp | Q29: Ironico
A30: CLI-03 | B30: Clienti e mercato | C30: La Gazzetta del Muletto | D30: Matrimonio del figlio del cliente | E30: Il titolare del Pastificio Rummolo ti invita al matrimonio del figlio, a Benevento. | F30: Clienti con soddisfazione alta | G30: 2002 | H30: 2040 | I30: Rara | J30: Vai con un regalo all'altezza | K30: −2.500 €, soddisfazione +15 | L30: Manda un biglietto | M30: Soddisfazione −5 | Q30: Ironico
A31: CLI-04 | B31: Clienti e mercato | C31: Il Sole 24 Pallet | D31: Un cliente fallisce | E31: Un tuo cliente porta i libri in tribunale. Le fatture degli ultimi 3 mesi non saranno pagate. | F31: Clienti con finanze deboli | G31: 2002 | H31: 2040 | I31: Rara | J31: Insinuati nel fallimento | K31: Recuperi il 20% in 2 anni | L31: Vendi la merce rimasta in magazzino | M31: Recuperi il 40% subito, 20% di contestazioni legali | Q31: Serio
A32: CLI-05 | B32: Clienti e mercato | C32: La Gazzetta del Muletto | D32: Ordine alle 17:58 di venerdì | E32: "Ci serve per lunedì alle 6, è vitale." | F32: Qualsiasi cliente | G32: 2002 | H32: 2040 | I32: Comune | J32: Accetta | K32: Straordinari −2.000 €, morale −4, soddisfazione +8 | L32: Rifiuta con cortesia | M32: Soddisfazione −6 | Q32: Ironico
A33: CLI-06 | B33: Clienti e mercato | C33: Il Sole 24 Pallet | D33: Crisi finanziaria | E33: Le banche chiudono i rubinetti, i volumi calano in tutti i settori. | F33: Settembre 2008 | G33: 2008 | H33: 2008 | I33: Datato | J33: Taglia i costi | K33: Personale −10%, credibilità −10, cassa protetta | L33: Resisti senza licenziare | M33: Cassa sotto pressione per 18 mesi, credibilità +5 | Q33: Serio
A34: CLI-07 | B34: Clienti e mercato | C34: Il Sole 24 Pallet | D34: Pandemia e lockdown | E34: Il Paese si ferma. Alimentare, farmaceutico ed e-commerce esplodono, il resto crolla. | F34: Marzo 2020 | G34: 2020 | H34: 2020 | I34: Datato | J34: Proteggi il personale (dispositivi, turni) | K34: −20.000 €, morale +10, produttività −10% | L34: Massima produzione | M34: Produttività +10%, rischio contagi e assenze, credibilità −8 | Q34: Serio
A35: CON-01 | B35: Concorrenti | C35: Il Sole 24 Pallet | D35: Pranzo con Klaus Effizienz | E35: Il CEO di Logistix Global ti invita a pranzo: "Solo per conoscerci". | F35: Azienda in crescita | G35: 2002 | H35: 2040 | I35: Rara | J35: Ascolta l'offerta | K35: Ricevi un'offerta di acquisto | L35: Declina | M35: Opinione di Logistix −10 | N35: Bluffa su un accordo con un altro gruppo | O35: Negoziazione ≥ 16 | P35: Logistix non attacca le tue province per 2 anni | Q35: Ironico | R35: CON-01b L'offerta formale
A36: CON-02 | B36: Concorrenti | C36: La Gazzetta del Muletto | D36: Lite dai Fratelli Brambilla | E36: I fratelli Brambilla litigano sull'eredità. Il minore ti offre i suoi clienti se lo assumi. | F36: Dopo la morte del fondatore dei Brambilla | G36: 2002 | H36: 2040 | I36: Rara | J36: Assumilo come manager | K36: Nuovo manager (Negoziazione alta) e 2 clienti; opinione dei Brambilla −30 | L36: Rifiuta | M36: Opinione dei Brambilla +10 | Q36: Ironico
A37: CON-03 | B37: Concorrenti | C37: Il Sole 24 Pallet | D37: Consegne in 2 ore | E37: Spedisci.io lancia le consegne in 2 ore a Milano. Due tuoi clienti chiedono perché tu non lo fai. | F37: Dal 2014; clienti in provincia di Milano | G37: 2014 | H37: 2040 | I37: Comune | J37: Avvia un progetto pilota | K37: −30.000 €, sblocca il servizio Express | L37: Spiega che non serve | M37: Soddisfazione −5 per 2 clienti | Q37: Ironico
A39: Riepilogo
A40: Categoria | C40: Eventi
A41: Meteo e strade | C41: =COUNTIF($B$5:$B$37,A41) -> 5
A42: Politica e burocrazia | C42: =COUNTIF($B$5:$B$37,A42) -> 6
A43: Vita locale | C43: =COUNTIF($B$5:$B$37,A43) -> 6
A44: Personale | C44: =COUNTIF($B$5:$B$37,A44) -> 6
A45: Clienti e mercato | C45: =COUNTIF($B$5:$B$37,A45) -> 7
A46: Concorrenti | C46: =COUNTIF($B$5:$B$37,A46) -> 3
A47: Totale | C47: =SUM(C41:C46) -> 33

Sheet Simulazione
A1: Simulazione: Gino Bertolotti a Rivalta Scrivia, 24 mesi
A2: Modello mensile semplificato. Cambia le celle in blu (parametri, clienti, mesi di investimento) e la simulazione si ricalcola. Mese di inizio 0 = cliente o tecnologia esclusi.
A4: Parametri | D4: Gino (CEO e manager di Rivalta)
A5: Cassa iniziale (€) | B5: 180000 | D5: Operazioni | E5: 17
A6: Capienza magazzino (posti pallet) | B6: 2500 | D6: Precisione | E6: 9
A7: Tariffa stoccaggio (€/posto/mese) | B7: 5.5 | D7: Leadership | E7: 14
A8: Tariffa movimentazione (€/pallet mosso) | B8: 3.8 | D8: Allergico al gestionale (1 = sì) | E8: 1
A9: Tariffa distribuzione (€/pallet consegnato) | B9: 30
A10: RAL magazziniere (€) | B10: 18500 | D10: Tecnologie | E10: Mese di avvio | F10: Accuratezza (pp) | G10: Puntualità (pp) | H10: Costo una tantum (€) | I10: Canone (€/mese) | J10: Settimane di apprendimento
A11: RAL autista (€) | B11: 20000 | D11: Lettori barcode | E11: 3 | F11: 1.5 | G11: 0 | H11: 12000 | I11: 150 | J11: 2
A12: RAL impiegato (€) | B12: 22000 | D12: WMS di base | E12: 0 | F12: 1.5 | G12: 0.5 | H12: 65000 | I12: 800 | J12: 6
A13: Coefficiente costo azienda | B13: 1.42 | D13: Durante l'apprendimento la tecnologia toglie metà del suo effetto; "Allergico al gestionale" allunga l'apprendimento del 50%.
A14: Compenso CEO (€/mese) | B14: 4000
A15: Immobile: manutenzione e utenze (€/mese) | B15: 3500 | D15: Clienti
A16: Spese varie (€/mese) | B16: 1500 | D16: Cliente | E16: Mese di inizio | F16: Stock medio (posti) | G16: Pallet consegnati/mese | H16: Soglia puntualità (%) | I16: Soglia accuratezza (%)
A17: Produttività magazziniere (pallet mossi/mese) | B17: 900 | D17: Pastificio Rummolo | E17: 1 | F17: 700 | G17: 300 | H17: 92
A18: Pallet per viaggio (motrice) | B18: 16 | D18: Caseificio Galbanone | E18: 4 | F18: 600 | G18: 480 | H18: 93 | I18: 96
A19: Km per viaggio | B19: 240 | D19: Ferramenta Bullonati | E19: 9 | F19: 500 | G19: 250 | H19: 90 | I19: 97
A20: Viaggi al mese per autista | B20: 20 | D20: Esselonga | E20: 0 | F20: 1500 | G20: 2400 | H20: 98 | I20: 95
A21: Prezzo gasolio (€/l) | B21: 0.86 | D21: Soglia accuratezza vuota = KPI non richiesto. Esselonga è esclusa (mese 0): metti 4 per provare un contratto troppo grande.
A22: Consumo motrice (l/km) | B22: 0.25 | D22: Soddisfazione: parte da 60; +3 al mese sopra soglia, −4 se sotto di 2 punti al massimo, −10 e penale del 5% se oltre. Sotto 25 il cliente se ne va.
A23: Pedaggi (€/km) | B23: 0.08
A24: Usura (€/km) | B24: 0.05 | D24: Risultato | G24: Risultati delle prove (valori fissi, da 24 mesi di simulazione)
A25: Costi fissi per motrice (€/mese) | B25: 1100 | D25: Cassa minima (€) | E25: =MIN(AB39:AB62) -> 142365.4 | G25: Prova | H25: Scelte | I25: Cassa minima (€) | J25: Cassa a 24 mesi (€) | K25: Cassa sotto zero | L25: Clienti persi
A26: Leasing motrice aggiuntiva (€/mese) | B26: 2100 | D26: Cassa a fine simulazione (€) | E26: =AB62 -> 260477.07 | G26: A | H26: Solo Rummolo, nessuna mossa | I26: -23877 | J26: -23877 | K26: mese 22 | L26: —
A27: Motrici di proprietà | B27: 3 | D27: Mese in cui la cassa va sotto zero | E27: =IFERROR(INDEX(A39:A62,MATCH(TRUE(),INDEX(AB39:AB62<0,0),0)),"mai") -> mai | G27: B | H27: Galbanone dal mese 4, Ferramenta dal 9, assunzioni in anticipo | I27: 132569 | J27: 132569 | K27: mai | L27: Galbanone, Ferramenta
A28: Pallet consegnati/mese per impiegato oltre i 2 minimi | B28: 1500 | D28: Utile medio degli ultimi 6 mesi (€/mese) | E28: =AVERAGE(AA57:AA62) -> 6355.1667 | G28: C | H28: Come B, ma assunzioni in ritardo di un mese | I28: 115138 | J28: 115138 | K28: mai | L28: Galbanone, Ferramenta
A29: Magazzinieri minimi | B29: 2 | D29: Clienti persi | E29: =AG62+AK62+AO62+AS62 -> 0 | G29: D | H29: Come B + barcode al mese 3 + WMS al mese 7 | I29: 89709 | J29: 181077 | K29: mai | L29: —
A30: Impiegati minimi | B30: 2 | G30: D2 | H30: Come B + solo barcode al mese 3 (impostazione attuale) | I30: 142365 | J30: 260477 | K30: mai | L30: —
A31: Puntualità di base (%) | B31: 92 | G31: E | H31: Rummolo + Esselonga dal mese 4 | I31: 93932 | J31: 93932 | K31: mai | L31: Esselonga
A32: Puntualità per punto di Operazioni sopra 10 | B32: 0.4
A33: Accuratezza di base (%) | B33: 96
A34: Accuratezza per punto di Precisione sopra 10 | B34: 0.3
A35: Assunzioni in ritardo di un mese (1 = sì, 0 = no) | B35: 0
A38: Mese | B38: Stock (posti) | C38: Saturazione | D38: Pallet consegnati | E38: Pallet mossi | F38: Viaggi | G38: Magazzinieri necessari | H38: Autisti necessari | I38: Impiegati necessari | J38: Magazzinieri | K38: Autisti | L38: Impiegati | M38: Produttività effettiva | N38: Carico magazzinieri | O38: Carico autisti | P38: Effetto tecn. accuratezza | Q38: Effetto tecn. puntualità | R38: Costo tecnologie (€) | S38: Puntualità (%) | T38: Accuratezza (%) | U38: Morale | V38: Ricavi (€) | W38: Personale (€) | X38: Mezzi (€) | Y38: Fissi (€) | Z38: Penali (€) | AA38: Utile (€) | AB38: Cassa (€) | AD38: Pastificio Rummolo – Attivo | AE38: Pastificio Rummolo – Scarto peggiore (pp) | AF38: Pastificio Rummolo – Soddisfazione | AG38: Pastificio Rummolo – Perso | AH38: Caseificio Galbanone – Attivo | AI38: Caseificio Galbanone – Scarto peggiore (pp) | AJ38: Caseificio Galbanone – Soddisfazione | AK38: Caseificio Galbanone – Perso | AL38: Ferramenta Bullonati – Attivo | AM38: Ferramenta Bullonati – Scarto peggiore (pp) | AN38: Ferramenta Bullonati – Soddisfazione | AO38: Ferramenta Bullonati – Perso | AP38: Esselonga – Attivo | AQ38: Esselonga – Scarto peggiore (pp) | AR38: Esselonga – Soddisfazione | AS38: Esselonga – Perso
A39: 1 | B39: =AD39*$F$17+AH39*$F$18+AL39*$F$19+AP39*$F$20 -> 700 | C39: =B39/$B$6 -> 0.28 | D39: =AD39*$G$17+AH39*$G$18+AL39*$G$19+AP39*$G$20 -> 300 | E39: =2*D39 -> 600 | F39: =ROUNDUP(D39/$B$18,0) -> 19 | G39: =MAX($B$29,ROUNDUP(E39/$B$17,0)) -> 2 | H39: =MAX(1,ROUNDUP(F39/$B$20,0)) -> 1 | I39: =$B$30+INT(D39/$B$28) -> 2 | J39: =G39 -> 2 | K39: =H39 -> 1 | L39: =I39 -> 2 | M39: =$B$17*(0.7+0.3*65/70) -> 880.71429 | N39: =E39/(J39*M39) -> 0.3406326 | O39: =F39/(K39*$B$20) -> 0.95 | P39: =$F$11*IF(AND($E$11>0,A39>=$E$11),IF((A39-$E$11+1)*4.3<=$J$11*IF($E$8=1,1.5,1),-0.5,1),0)+$F$12*IF(AND($E$12>0,A39>=$E$12),IF((A39-$E$12+1)*4.3<=$J$12*IF($E$8=1,1.5,1),-0.5,1),0) -> 0 | Q39: =$G$11*IF(AND($E$11>0,A39>=$E$11),IF((A39-$E$11+1)*4.3<=$J$11*IF($E$8=1,1.5,1),-0.5,1),0)+$G$12*IF(AND($E$12>0,A39>=$E$12),IF((A39-$E$12+1)*4.3<=$J$12*IF($E$8=1,1.5,1),-0.5,1),0) -> 0 | R39: =IF(AND($E$11>0,A39=$E$11),$H$11,0)+IF(AND($E$11>0,A39>=$E$11),$I$11,0)+IF(AND($E$12>0,A39=$E$12),$H$12,0)+IF(AND($E$12>0,A39>=$E$12),$I$12,0) -> 0 | S39: =MAX(50,MIN(99.9,$B$31+$B$32*($E$5-10)+Q39-20*MAX(0,O39-1)-5*MAX(0,N39-1.05))) -> 94.8 | T39: =MAX(50,MIN(99.9,$B$33+$B$34*($E$6-10)+0.04*(65-60)+P39-25*MAX(0,C39-0.85)-8*MAX(0,N39-1))) -> 95.9 | U39: =MAX(0,MIN(100,65+0.35*(58+0.6*($E$7-10)-30*MAX(0,N39-1)-20*MAX(0,O39-1)-65))) -> 63.39 | V39: =B39*$B$7+E39*$B$8+D39*$B$9 -> 15130 | W39: =(J39*$B$10+K39*$B$11+L39*$B$12)*$B$13/12 -> 11951.667 | X39: =F39*$B$19*($B$22*$B$21+$B$23+$B$24)+K39*$B$25+MAX(0,K39-$B$27)*$B$26 -> 2673.2 | Y39: =$B$14+$B$15+$B$16 -> 9000 | Z39: =IF(AND(AD39=1,AE39<-2),0.05*($F$17*$B$7+2*$G$17*$B$8+$G$17*$B$9),0)+IF(AND(AH39=1,AI39<-2),0.05*($F$18*$B$7+2*$G$18*$B$8+$G$18*$B$9),0)+IF(AND(AL39=1,AM39<-2),0.05*($F$19*$B$7+2*$G$19*$B$8+$G$19*$B$9),0)+IF(AND(AP39=1,AQ39<-2),0.05*($F$20*$B$7+2*$G$20*$B$8+$G$20*$B$9),0) -> 0 | AA39: =V39-W39-X39-Y39-R39-Z39 -> -8494.8667 | AB39: =$B$5+AA39 -> 171505.13 | AD39: =IF(AND($E$17>0,A39>=$E$17,0=0),1,0) -> 1 | AE39: =IF(AD39=1,MIN(S39-$H$17,IF($I$17="",9,T39-$I$17)),"") -> 2.8 | AF39: =IF(AD39=1,MAX(0,MIN(100,60+IF(AE39>=0,3,IF(AE39>=-2,-4,-10)))),60) -> 63 | AG39: =IF(OR(0=1,AND(AD39=1,AF39<25)),1,0) -> 0 | AH39: =IF(AND($E$18>0,A39>=$E$18,0=0),1,0) -> 0 | AI39: =IF(AH39=1,MIN(S39-$H$18,IF($I$18="",9,T39-$I$18)),"") | AJ39: =IF(AH39=1,MAX(0,MIN(100,60+IF(AI39>=0,3,IF(AI39>=-2,-4,-10)))),60) -> 60 | AK39: =IF(OR(0=1,AND(AH39=1,AJ39<25)),1,0) -> 0 | AL39: =IF(AND($E$19>0,A39>=$E$19,0=0),1,0) -> 0 | AM39: =IF(AL39=1,MIN(S39-$H$19,IF($I$19="",9,T39-$I$19)),"") | AN39: =IF(AL39=1,MAX(0,MIN(100,60+IF(AM39>=0,3,IF(AM39>=-2,-4,-10)))),60) -> 60 | AO39: =IF(OR(0=1,AND(AL39=1,AN39<25)),1,0) -> 0 | AP39: =IF(AND($E$20>0,A39>=$E$20,0=0),1,0) -> 0 | AQ39: =IF(AP39=1,MIN(S39-$H$20,IF($I$20="",9,T39-$I$20)),"") | AR39: =IF(AP39=1,MAX(0,MIN(100,60+IF(AQ39>=0,3,IF(AQ39>=-2,-4,-10)))),60) -> 60 | AS39: =IF(OR(0=1,AND(AP39=1,AR39<25)),1,0) -> 0
A40: 2 | B40: =AD40*$F$17+AH40*$F$18+AL40*$F$19+AP40*$F$20 -> 700 | C40: =B40/$B$6 -> 0.28 | D40: =AD40*$G$17+AH40*$G$18+AL40*$G$19+AP40*$G$20 -> 300 | E40: =2*D40 -> 600 | F40: =ROUNDUP(D40/$B$18,0) -> 19 | G40: =MAX($B$29,ROUNDUP(E40/$B$17,0)) -> 2 | H40: =MAX(1,ROUNDUP(F40/$B$20,0)) -> 1 | I40: =$B$30+INT(D40/$B$28) -> 2 | J40: =IF($B$35=1,G39,G40) -> 2 | K40: =IF($B$35=1,H39,H40) -> 1 | L40: =IF($B$35=1,I39,I40) -> 2 | M40: =$B$17*(0.7+0.3*U39/70) -> 874.50429 | N40: =E40/(J40*M40) -> 0.34305149 | O40: =F40/(K40*$B$20) -> 0.95 | P40: =$F$11*IF(AND($E$11>0,A40>=$E$11),IF((A40-$E$11+1)*4.3<=$J$11*IF($E$8=1,1.5,1),-0.5,1),0)+$F$12*IF(AND($E$12>0,A40>=$E$12),IF((A40-$E$12+1)*4.3<=$J$12*IF($E$8=1,1.5,1),-0.5,1),0) -> 0 | Q40: =$G$11*IF(AND($E$11>0,A40>=$E$11),IF((A40-$E$11+1)*4.3<=$J$11*IF($E$8=1,1.5,1),-0.5,1),0)+$G$12*IF(AND($E$12>0,A40>=$E$12),IF((A40-$E$12+1)*4.3<=$J$12*IF($E$8=1,1.5,1),-0.5,1),0) -> 0 | R40: =IF(AND($E$11>0,A40=$E$11),$H$11,0)+IF(AND($E$11>0,A40>=$E$11),$I$11,0)+IF(AND($E$12>0,A40=$E$12),$H$12,0)+IF(AND($E$12>0,A40>=$E$12),$I$12,0) -> 0 | S40: =MAX(50,MIN(99.9,$B$31+$B$32*($E$5-10)+Q40-20*MAX(0,O40-1)-5*MAX(0,N40-1.05))) -> 94.8 | T40: =MAX(50,MIN(99.9,$B$33+$B$34*($E$6-10)+0.04*(U39-60)+P40-25*MAX(0,C40-0.85)-8*MAX(0,N40-1))) -> 95.8356 | U40: =MAX(0,MIN(100,U39+0.35*(58+0.6*($E$7-10)-30*MAX(0,N40-1)-20*MAX(0,O40-1)-U39))) -> 62.3435 | V40: =B40*$B$7+E40*$B$8+D40*$B$9 -> 15130 | W40: =(J40*$B$10+K40*$B$11+L40*$B$12)*$B$13/12 -> 11951.667 | X40: =F40*$B$19*($B$22*$B$21+$B$23+$B$24)+K40*$B$25+MAX(0,K40-$B$27)*$B$26 -> 2673.2 | Y40: =$B$14+$B$15+$B$16 -> 9000 | Z40: =IF(AND(AD40=1,AE40<-2),0.05*($F$17*$B$7+2*$G$17*$B$8+$G$17*$B$9),0)+IF(AND(AH40=1,AI40<-2),0.05*($F$18*$B$7+2*$G$18*$B$8+$G$18*$B$9),0)+IF(AND(AL40=1,AM40<-2),0.05*($F$19*$B$7+2*$G$19*$B$8+$G$19*$B$9),0)+IF(AND(AP40=1,AQ40<-2),0.05*($F$20*$B$7+2*$G$20*$B$8+$G$20*$B$9),0) -> 0 | AA40: =V40-W40-X40-Y40-R40-Z40 -> -8494.8667 | AB40: =AB39+AA40 -> 163010.27 | AD40: =IF(AND($E$17>0,A40>=$E$17,AG39=0),1,0) -> 1 | AE40: =IF(AD40=1,MIN(S40-$H$17,IF($I$17="",9,T40-$I$17)),"") -> 2.8 | AF40: =IF(AD40=1,MAX(0,MIN(100,AF39+IF(AE40>=0,3,IF(AE40>=-2,-4,-10)))),AF39) -> 66 | AG40: =IF(OR(AG39=1,AND(AD40=1,AF40<25)),1,0) -> 0 | AH40: =IF(AND($E$18>0,A40>=$E$18,AK39=0),1,0) -> 0 | AI40: =IF(AH40=1,MIN(S40-$H$18,IF($I$18="",9,T40-$I$18)),"") | AJ40: =IF(AH40=1,MAX(0,MIN(100,AJ39+IF(AI40>=0,3,IF(AI40>=-2,-4,-10)))),AJ39) -> 60 | AK40: =IF(OR(AK39=1,AND(AH40=1,AJ40<25)),1,0) -> 0 | AL40: =IF(AND($E$19>0,A40>=$E$19,AO39=0),1,0) -> 0 | AM40: =IF(AL40=1,MIN(S40-$H$19,IF($I$19="",9,T40-$I$19)),"") | AN40: =IF(AL40=1,MAX(0,MIN(100,AN39+IF(AM40>=0,3,IF(AM40>=-2,-4,-10)))),AN39) -> 60 | AO40: =IF(OR(AO39=1,AND(AL40=1,AN40<25)),1,0) -> 0 | AP40: =IF(AND($E$20>0,A40>=$E$20,AS39=0),1,0) -> 0 | AQ40: =IF(AP40=1,MIN(S40-$H$20,IF($I$20="",9,T40-$I$20)),"") | AR40: =IF(AP40=1,MAX(0,MIN(100,AR39+IF(AQ40>=0,3,IF(AQ40>=-2,-4,-10)))),AR39) -> 60 | AS40: =IF(OR(AS39=1,AND(AP40=1,AR40<25)),1,0) -> 0
A41: 3 | B41: =AD41*$F$17+AH41*$F$18+AL41*$F$19+AP41*$F$20 -> 700 | C41: =B41/$B$6 -> 0.28 | D41: =AD41*$G$17+AH41*$G$18+AL41*$G$19+AP41*$G$20 -> 300 | E41: =2*D41 -> 600 | F41: =ROUNDUP(D41/$B$18,0) -> 19 | G41: =MAX($B$29,ROUNDUP(E41/$B$17,0)) -> 2 | H41: =MAX(1,ROUNDUP(F41/$B$20,0)) -> 1 | I41: =$B$30+INT(D41/$B$28) -> 2 | J41: =IF($B$35=1,G40,G41) -> 2 | K41: =IF($B$35=1,H40,H41) -> 1 | L41: =IF($B$35=1,I40,I41) -> 2 | M41: =$B$17*(0.7+0.3*U40/70) -> 870.46779 | N41: =E41/(J41*M41) -> 0.34464228 | O41: =F41/(K41*$B$20) -> 0.95 | P41: =$F$11*IF(AND($E$11>0,A41>=$E$11),IF((A41-$E$11+1)*4.3<=$J$11*IF($E$8=1,1.5,1),-0.5,1),0)+$F$12*IF(AND($E$12>0,A41>=$E$12),IF((A41-$E$12+1)*4.3<=$J$12*IF($E$8=1,1.5,1),-0.5,1),0) -> 1.5 | Q41: =$G$11*IF(AND($E$11>0,A41>=$E$11),IF((A41-$E$11+1)*4.3<=$J$11*IF($E$8=1,1.5,1),-0.5,1),0)+$G$12*IF(AND($E$12>0,A41>=$E$12),IF((A41-$E$12+1)*4.3<=$J$12*IF($E$8=1,1.5,1),-0.5,1),0) -> 0 | R41: =IF(AND($E$11>0,A41=$E$11),$H$11,0)+IF(AND($E$11>0,A41>=$E$11),$I$11,0)+IF(AND($E$12>0,A41=$E$12),$H$12,0)+IF(AND($E$12>0,A41>=$E$12),$I$12,0) -> 12150 | S41: =MAX(50,MIN(99.9,$B$31+$B$32*($E$5-10)+Q41-20*MAX(0,O41-1)-5*MAX(0,N41-1.05))) -> 94.8 | T41: =MAX(50,MIN(99.9,$B$33+$B$34*($E$6-10)+0.04*(U40-60)+P41-25*MAX(0,C41-0.85)-8*MAX(0,N41-1))) -> 97.29374 | U41: =MAX(0,MIN(100,U40+0.35*(58+0.6*($E$7-10)-30*MAX(0,N41-1)-20*MAX(0,O41-1)-U40))) -> 61.663275 | V41: =B41*$B$7+E41*$B$8+D41*$B$9 -> 15130 | W41: =(J41*$B$10+K41*$B$11+L41*$B$12)*$B$13/12 -> 11951.667 | X41: =F41*$B$19*($B$22*$B$21+$B$23+$B$24)+K41*$B$25+MAX(0,K41-$B$27)*$B$26 -> 2673.2 | Y41: =$B$14+$B$15+$B$16 -> 9000 | Z41: =IF(AND(AD41=1,AE41<-2),0.05*($F$17*$B$7+2*$G$17*$B$8+$G$17*$B$9),0)+IF(AND(AH41=1,AI41<-2),0.05*($F$18*$B$7+2*$G$18*$B$8+$G$18*$B$9),0)+IF(AND(AL41=1,AM41<-2),0.05*($F$19*$B$7+2*$G$19*$B$8+$G$19*$B$9),0)+IF(AND(AP41=1,AQ41<-2),0.05*($F$20*$B$7+2*$G$20*$B$8+$G$20*$B$9),0) -> 0 | AA41: =V41-W41-X41-Y41-R41-Z41 -> -20644.867 | AB41: =AB40+AA41 -> 142365.4 | AD41: =IF(AND($E$17>0,A41>=$E$17,AG40=0),1,0) -> 1 | AE41: =IF(AD41=1,MIN(S41-$H$17,IF($I$17="",9,T41-$I$17)),"") -> 2.8 | AF41: =IF(AD41=1,MAX(0,MIN(100,AF40+IF(AE41>=0,3,IF(AE41>=-2,-4,-10)))),AF40) -> 69 | AG41: =IF(OR(AG40=1,AND(AD41=1,AF41<25)),1,0) -> 0 | AH41: =IF(AND($E$18>0,A41>=$E$18,AK40=0),1,0) -> 0 | AI41: =IF(AH41=1,MIN(S41-$H$18,IF($I$18="",9,T41-$I$18)),"") | AJ41: =IF(AH41=1,MAX(0,MIN(100,AJ40+IF(AI41>=0,3,IF(AI41>=-2,-4,-10)))),AJ40) -> 60 | AK41: =IF(OR(AK40=1,AND(AH41=1,AJ41<25)),1,0) -> 0 | AL41: =IF(AND($E$19>0,A41>=$E$19,AO40=0),1,0) -> 0 | AM41: =IF(AL41=1,MIN(S41-$H$19,IF($I$19="",9,T41-$I$19)),"") | AN41: =IF(AL41=1,MAX(0,MIN(100,AN40+IF(AM41>=0,3,IF(AM41>=-2,-4,-10)))),AN40) -> 60 | AO41: =IF(OR(AO40=1,AND(AL41=1,AN41<25)),1,0) -> 0 | AP41: =IF(AND($E$20>0,A41>=$E$20,AS40=0),1,0) -> 0 | AQ41: =IF(AP41=1,MIN(S41-$H$20,IF($I$20="",9,T41-$I$20)),"") | AR41: =IF(AP41=1,MAX(0,MIN(100,AR40+IF(AQ41>=0,3,IF(AQ41>=-2,-4,-10)))),AR40) -> 60 | AS41: =IF(OR(AS40=1,AND(AP41=1,AR41<25)),1,0) -> 0
A42: 4 | B42: =AD42*$F$17+AH42*$F$18+AL42*$F$19+AP42*$F$20 -> 1300 | C42: =B42/$B$6 -> 0.52 | D42: =AD42*$G$17+AH42*$G$18+AL42*$G$19+AP42*$G$20 -> 780 | E42: =2*D42 -> 1560 | F42: =ROUNDUP(D42/$B$18,0) -> 49 | G42: =MAX($B$29,ROUNDUP(E42/$B$17,0)) -> 2 | H42: =MAX(1,ROUNDUP(F42/$B$20,0)) -> 3 | I42: =$B$30+INT(D42/$B$28) -> 2 | J42: =IF($B$35=1,G41,G42) -> 2 | K42: =IF($B$35=1,H41,H42) -> 3 | L42: =IF($B$35=1,I41,I42) -> 2 | M42: =$B$17*(0.7+0.3*U41/70) -> 867.84406 | N42: =E42/(J42*M42) -> 0.89877898 | O42: =F42/(K42*$B$20) -> 0.81666667 | P42: =$F$11*IF(AND($E$11>0,A42>=$E$11),IF((A42-$E$11+1)*4.3<=$J$11*IF($E$8=1,1.5,1),-0.5,1),0)+$F$12*IF(AND($E$12>0,A42>=$E$12),IF((A42-$E$12+1)*4.3<=$J$12*IF($E$8=1,1.5,1),-0.5,1),0) -> 1.5 | Q42: =$G$11*IF(AND($E$11>0,A42>=$E$11),IF((A42-$E$11+1)*4.3<=$J$11*IF($E$8=1,1.5,1),-0.5,1),0)+$G$12*IF(AND($E$12>0,A42>=$E$12),IF((A42-$E$12+1)*4.3<=$J$12*IF($E$8=1,1.5,1),-0.5,1),0) -> 0 | R42: =IF(AND($E$11>0,A42=$E$11),$H$11,0)+IF(AND($E$11>0,A42>=$E$11),$I$11,0)+IF(AND($E$12>0,A42=$E$12),$H$12,0)+IF(AND($E$12>0,A42>=$E$12),$I$12,0) -> 150 | S42: =MAX(50,MIN(99.9,$B$31+$B$32*($E$5-10)+Q42-20*MAX(0,O42-1)-5*MAX(0,N42-1.05))) -> 94.8 | T42: =MAX(50,MIN(99.9,$B$33+$B$34*($E$6-10)+0.04*(U41-60)+P42-25*MAX(0,C42-0.85)-8*MAX(0,N42-1))) -> 97.266531 | U42: =MAX(0,MIN(100,U41+0.35*(58+0.6*($E$7-10)-30*MAX(0,N42-1)-20*MAX(0,O42-1)-U41))) -> 61.221129 | V42: =B42*$B$7+E42*$B$8+D42*$B$9 -> 36478 | W42: =(J42*$B$10+K42*$B$11+L42*$B$12)*$B$13/12 -> 16685 | X42: =F42*$B$19*($B$22*$B$21+$B$23+$B$24)+K42*$B$25+MAX(0,K42-$B$27)*$B$26 -> 7357.2 | Y42: =$B$14+$B$15+$B$16 -> 9000 | Z42: =IF(AND(AD42=1,AE42<-2),0.05*($F$17*$B$7+2*$G$17*$B$8+$G$17*$B$9),0)+IF(AND(AH42=1,AI42<-2),0.05*($F$18*$B$7+2*$G$18*$B$8+$G$18*$B$9),0)+IF(AND(AL42=1,AM42<-2),0.05*($F$19*$B$7+2*$G$19*$B$8+$G$19*$B$9),0)+IF(AND(AP42=1,AQ42<-2),0.05*($F$20*$B$7+2*$G$20*$B$8+$G$20*$B$9),0) -> 0 | AA42: =V42-W42-X42-Y42-R42-Z42 -> 3285.8 | AB42: =AB41+AA42 -> 145651.2 | AD42: =IF(AND($E$17>0,A42>=$E$17,AG41=0),1,0) -> 1 | AE42: =IF(AD42=1,MIN(S42-$H$17,IF($I$17="",9,T42-$I$17)),"") -> 2.8 | AF42: =IF(AD42=1,MAX(0,MIN(100,AF41+IF(AE42>=0,3,IF(AE42>=-2,-4,-10)))),AF41) -> 72 | AG42: =IF(OR(AG41=1,AND(AD42=1,AF42<25)),1,0) -> 0 | AH42: =IF(AND($E$18>0,A42>=$E$18,AK41=0),1,0) -> 1 | AI42: =IF(AH42=1,MIN(S42-$H$18,IF($I$18="",9,T42-$I$18)),"") -> 1.266531 | AJ42: =IF(AH42=1,MAX(0,MIN(100,AJ41+IF(AI42>=0,3,IF(AI42>=-2,-4,-10)))),AJ41) -> 63 | AK42: =IF(OR(AK41=1,AND(AH42=1,AJ42<25)),1,0) -> 0 | AL42: =IF(AND($E$19>0,A42>=$E$19,AO41=0),1,0) -> 0 | AM42: =IF(AL42=1,MIN(S42-$H$19,IF($I$19="",9,T42-$I$19)),"") | AN42: =IF(AL42=1,MAX(0,MIN(100,AN41+IF(AM42>=0,3,IF(AM42>=-2,-4,-10)))),AN41) -> 60 | AO42: =IF(OR(AO41=1,AND(AL42=1,AN42<25)),1,0) -> 0 | AP42: =IF(AND($E$20>0,A42>=$E$20,AS41=0),1,0) -> 0 | AQ42: =IF(AP42=1,MIN(S42-$H$20,IF($I$20="",9,T42-$I$20)),"") | AR42: =IF(AP42=1,MAX(0,MIN(100,AR41+IF(AQ42>=0,3,IF(AQ42>=-2,-4,-10)))),AR41) -> 60 | AS42: =IF(OR(AS41=1,AND(AP42=1,AR42<25)),1,0) -> 0
A43: 5 | B43: =AD43*$F$17+AH43*$F$18+AL43*$F$19+AP43*$F$20 -> 1300 | C43: =B43/$B$6 -> 0.52 | D43: =AD43*$G$17+AH43*$G$18+AL43*$G$19+AP43*$G$20 -> 780 | E43: =2*D43 -> 1560 | F43: =ROUNDUP(D43/$B$18,0) -> 49 | G43: =MAX($B$29,ROUNDUP(E43/$B$17,0)) -> 2 | H43: =MAX(1,ROUNDUP(F43/$B$20,0)) -> 3 | I43: =$B$30+INT(D43/$B$28) -> 2 | J43: =IF($B$35=1,G42,G43) -> 2 | K43: =IF($B$35=1,H42,H43) -> 3 | L43: =IF($B$35=1,I42,I43) -> 2 | M43: =$B$17*(0.7+0.3*U42/70) -> 866.13864 | N43: =E43/(J43*M43) -> 0.90054867 | O43: =F43/(K43*$B$20) -> 0.81666667 | P43: =$F$11*IF(AND($E$11>0,A43>=$E$11),IF((A43-$E$11+1)*4.3<=$J$11*IF($E$8=1,1.5,1),-0.5,1),0)+$F$12*IF(AND($E$12>0,A43>=$E$12),IF((A43-$E$12+1)*4.3<=$J$12*IF($E$8=1,1.5,1),-0.5,1),0) -> 1.5 | Q43: =$G$11*IF(AND($E$11>0,A43>=$E$11),IF((A43-$E$11+1)*4.3<=$J$11*IF($E$8=1,1.5,1),-0.5,1),0)+$G$12*IF(AND($E$12>0,A43>=$E$12),IF((A43-$E$12+1)*4.3<=$J$12*IF($E$8=1,1.5,1),-0.5,1),0) -> 0 | R43: =IF(AND($E$11>0,A43=$E$11),$H$11,0)+IF(AND($E$11>0,A43>=$E$11),$I$11,0)+IF(AND($E$12>0,A43=$E$12),$H$12,0)+IF(AND($E$12>0,A43>=$E$12),$I$12,0) -> 150 | S43: =MAX(50,MIN(99.9,$B$31+$B$32*($E$5-10)+Q43-20*MAX(0,O43-1)-5*MAX(0,N43-1.05))) -> 94.8 | T43: =MAX(50,MIN(99.9,$B$33+$B$34*($E$6-10)+0.04*(U42-60)+P43-25*MAX(0,C43-0.85)-8*MAX(0,N43-1))) -> 97.248845 | U43: =MAX(0,MIN(100,U42+0.35*(58+0.6*($E$7-10)-30*MAX(0,N43-1)-20*MAX(0,O43-1)-U42))) -> 60.933734 | V43: =B43*$B$7+E43*$B$8+D43*$B$9 -> 36478 | W43: =(J43*$B$10+K43*$B$11+L43*$B$12)*$B$13/12 -> 16685 | X43: =F43*$B$19*($B$22*$B$21+$B$23+$B$24)+K43*$B$25+MAX(0,K43-$B$27)*$B$26 -> 7357.2 | Y43: =$B$14+$B$15+$B$16 -> 9000 | Z43: =IF(AND(AD43=1,AE43<-2),0.05*($F$17*$B$7+2*$G$17*$B$8+$G$17*$B$9),0)+IF(AND(AH43=1,AI43<-2),0.05*($F$18*$B$7+2*$G$18*$B$8+$G$18*$B$9),0)+IF(AND(AL43=1,AM43<-2),0.05*($F$19*$B$7+2*$G$19*$B$8+$G$19*$B$9),0)+IF(AND(AP43=1,AQ43<-2),0.05*($F$20*$B$7+2*$G$20*$B$8+$G$20*$B$9),0) -> 0 | AA43: =V43-W43-X43-Y43-R43-Z43 -> 3285.8 | AB43: =AB42+AA43 -> 148937 | AD43: =IF(AND($E$17>0,A43>=$E$17,AG42=0),1,0) -> 1 | AE43: =IF(AD43=1,MIN(S43-$H$17,IF($I$17="",9,T43-$I$17)),"") -> 2.8 | AF43: =IF(AD43=1,MAX(0,MIN(100,AF42+IF(AE43>=0,3,IF(AE43>=-2,-4,-10)))),AF42) -> 75 | AG43: =IF(OR(AG42=1,AND(AD43=1,AF43<25)),1,0) -> 0 | AH43: =IF(AND($E$18>0,A43>=$E$18,AK42=0),1,0) -> 1 | AI43: =IF(AH43=1,MIN(S43-$H$18,IF($I$18="",9,T43-$I$18)),"") -> 1.2488452 | AJ43: =IF(AH43=1,MAX(0,MIN(100,AJ42+IF(AI43>=0,3,IF(AI43>=-2,-4,-10)))),AJ42) -> 66 | AK43: =IF(OR(AK42=1,AND(AH43=1,AJ43<25)),1,0) -> 0 | AL43: =IF(AND($E$19>0,A43>=$E$19,AO42=0),1,0) -> 0 | AM43: =IF(AL43=1,MIN(S43-$H$19,IF($I$19="",9,T43-$I$19)),"") | AN43: =IF(AL43=1,MAX(0,MIN(100,AN42+IF(AM43>=0,3,IF(AM43>=-2,-4,-10)))),AN42) -> 60 | AO43: =IF(OR(AO42=1,AND(AL43=1,AN43<25)),1,0) -> 0 | AP43: =IF(AND($E$20>0,A43>=$E$20,AS42=0),1,0) -> 0 | AQ43: =IF(AP43=1,MIN(S43-$H$20,IF($I$20="",9,T43-$I$20)),"") | AR43: =IF(AP43=1,MAX(0,MIN(100,AR42+IF(AQ43>=0,3,IF(AQ43>=-2,-4,-10)))),AR42) -> 60 | AS43: =IF(OR(AS42=1,AND(AP43=1,AR43<25)),1,0) -> 0
A44: 6 | B44: =AD44*$F$17+AH44*$F$18+AL44*$F$19+AP44*$F$20 -> 1300 | C44: =B44/$B$6 -> 0.52 | D44: =AD44*$G$17+AH44*$G$18+AL44*$G$19+AP44*$G$20 -> 780 | E44: =2*D44 -> 1560 | F44: =ROUNDUP(D44/$B$18,0) -> 49 | G44: =MAX($B$29,ROUNDUP(E44/$B$17,0)) -> 2 | H44: =MAX(1,ROUNDUP(F44/$B$20,0)) -> 3 | I44: =$B$30+INT(D44/$B$28) -> 2 | J44: =IF($B$35=1,G43,G44) -> 2 | K44: =IF($B$35=1,H43,H44) -> 3 | L44: =IF($B$35=1,I43,I44) -> 2 | M44: =$B$17*(0.7+0.3*U43/70) -> 865.03012 | N44: =E44/(J44*M44) -> 0.90170271 | O44: =F44/(K44*$B$20) -> 0.81666667 | P44: =$F$11*IF(AND($E$11>0,A44>=$E$11),IF((A44-$E$11+1)*4.3<=$J$11*IF($E$8=1,1.5,1),-0.5,1),0)+$F$12*IF(AND($E$12>0,A44>=$E$12),IF((A44-$E$12+1)*4.3<=$J$12*IF($E$8=1,1.5,1),-0.5,1),0) -> 1.5 | Q44: =$G$11*IF(AND($E$11>0,A44>=$E$11),IF((A44-$E$11+1)*4.3<=$J$11*IF($E$8=1,1.5,1),-0.5,1),0)+$G$12*IF(AND($E$12>0,A44>=$E$12),IF((A44-$E$12+1)*4.3<=$J$12*IF($E$8=1,1.5,1),-0.5,1),0) -> 0 | R44: =IF(AND($E$11>0,A44=$E$11),$H$11,0)+IF(AND($E$11>0,A44>=$E$11),$I$11,0)+IF(AND($E$12>0,A44=$E$12),$H$12,0)+IF(AND($E$12>0,A44>=$E$12),$I$12,0) -> 150 | S44: =MAX(50,MIN(99.9,$B$31+$B$32*($E$5-10)+Q44-20*MAX(0,O44-1)-5*MAX(0,N44-1.05))) -> 94.8 | T44: =MAX(50,MIN(99.9,$B$33+$B$34*($E$6-10)+0.04*(U43-60)+P44-25*MAX(0,C44-0.85)-8*MAX(0,N44-1))) -> 97.237349 | U44: =MAX(0,MIN(100,U43+0.35*(58+0.6*($E$7-10)-30*MAX(0,N44-1)-20*MAX(0,O44-1)-U43))) -> 60.746927 | V44: =B44*$B$7+E44*$B$8+D44*$B$9 -> 36478 | W44: =(J44*$B$10+K44*$B$11+L44*$B$12)*$B$13/12 -> 16685 | X44: =F44*$B$19*($B$22*$B$21+$B$23+$B$24)+K44*$B$25+MAX(0,K44-$B$27)*$B$26 -> 7357.2 | Y44: =$B$14+$B$15+$B$16 -> 9000 | Z44: =IF(AND(AD44=1,AE44<-2),0.05*($F$17*$B$7+2*$G$17*$B$8+$G$17*$B$9),0)+IF(AND(AH44=1,AI44<-2),0.05*($F$18*$B$7+2*$G$18*$B$8+$G$18*$B$9),0)+IF(AND(AL44=1,AM44<-2),0.05*($F$19*$B$7+2*$G$19*$B$8+$G$19*$B$9),0)+IF(AND(AP44=1,AQ44<-2),0.05*($F$20*$B$7+2*$G$20*$B$8+$G$20*$B$9),0) -> 0 | AA44: =V44-W44-X44-Y44-R44-Z44 -> 3285.8 | AB44: =AB43+AA44 -> 152222.8 | AD44: =IF(AND($E$17>0,A44>=$E$17,AG43=0),1,0) -> 1 | AE44: =IF(AD44=1,MIN(S44-$H$17,IF($I$17="",9,T44-$I$17)),"") -> 2.8 | AF44: =IF(AD44=1,MAX(0,MIN(100,AF43+IF(AE44>=0,3,IF(AE44>=-2,-4,-10)))),AF43) -> 78 | AG44: =IF(OR(AG43=1,AND(AD44=1,AF44<25)),1,0) -> 0 | AH44: =IF(AND($E$18>0,A44>=$E$18,AK43=0),1,0) -> 1 | AI44: =IF(AH44=1,MIN(S44-$H$18,IF($I$18="",9,T44-$I$18)),"") -> 1.2373493 | AJ44: =IF(AH44=1,MAX(0,MIN(100,AJ43+IF(AI44>=0,3,IF(AI44>=-2,-4,-10)))),AJ43) -> 69 | AK44: =IF(OR(AK43=1,AND(AH44=1,AJ44<25)),1,0) -> 0 | AL44: =IF(AND($E$19>0,A44>=$E$19,AO43=0),1,0) -> 0 | AM44: =IF(AL44=1,MIN(S44-$H$19,IF($I$19="",9,T44-$I$19)),"") | AN44: =IF(AL44=1,MAX(0,MIN(100,AN43+IF(AM44>=0,3,IF(AM44>=-2,-4,-10)))),AN43) -> 60 | AO44: =IF(OR(AO43=1,AND(AL44=1,AN44<25)),1,0) -> 0 | AP44: =IF(AND($E$20>0,A44>=$E$20,AS43=0),1,0) -> 0 | AQ44: =IF(AP44=1,MIN(S44-$H$20,IF($I$20="",9,T44-$I$20)),"") | AR44: =IF(AP44=1,MAX(0,MIN(100,AR43+IF(AQ44>=0,3,IF(AQ44>=-2,-4,-10)))),AR43) -> 60 | AS44: =IF(OR(AS43=1,AND(AP44=1,AR44<25)),1,0) -> 0
A45: 7 | B45: =AD45*$F$17+AH45*$F$18+AL45*$F$19+AP45*$F$20 -> 1300 | C45: =B45/$B$6 -> 0.52 | D45: =AD45*$G$17+AH45*$G$18+AL45*$G$19+AP45*$G$20 -> 780 | E45: =2*D45 -> 1560 | F45: =ROUNDUP(D45/$B$18,0) -> 49 | G45: =MAX($B$29,ROUNDUP(E45/$B$17,0)) -> 2 | H45: =MAX(1,ROUNDUP(F45/$B$20,0)) -> 3 | I45: =$B$30+INT(D45/$B$28) -> 2 | J45: =IF($B$35=1,G44,G45) -> 2 | K45: =IF($B$35=1,H44,H45) -> 3 | L45: =IF($B$35=1,I44,I45) -> 2 | M45: =$B$17*(0.7+0.3*U44/70) -> 864.30958 | N45: =E45/(J45*M45) -> 0.90245442 | O45: =F45/(K45*$B$20) -> 0.81666667 | P45: =$F$11*IF(AND($E$11>0,A45>=$E$11),IF((A45-$E$11+1)*4.3<=$J$11*IF($E$8=1,1.5,1),-0.5,1),0)+$F$12*IF(AND($E$12>0,A45>=$E$12),IF((A45-$E$12+1)*4.3<=$J$12*IF($E$8=1,1.5,1),-0.5,1),0) -> 1.5 | Q45: =$G$11*IF(AND($E$11>0,A45>=$E$11),IF((A45-$E$11+1)*4.3<=$J$11*IF($E$8=1,1.5,1),-0.5,1),0)+$G$12*IF(AND($E$12>0,A45>=$E$12),IF((A45-$E$12+1)*4.3<=$J$12*IF($E$8=1,1.5,1),-0.5,1),0) -> 0 | R45: =IF(AND($E$11>0,A45=$E$11),$H$11,0)+IF(AND($E$11>0,A45>=$E$11),$I$11,0)+IF(AND($E$12>0,A45=$E$12),$H$12,0)+IF(AND($E$12>0,A45>=$E$12),$I$12,0) -> 150 | S45: =MAX(50,MIN(99.9,$B$31+$B$32*($E$5-10)+Q45-20*MAX(0,O45-1)-5*MAX(0,N45-1.05))) -> 94.8 | T45: =MAX(50,MIN(99.9,$B$33+$B$34*($E$6-10)+0.04*(U44-60)+P45-25*MAX(0,C45-0.85)-8*MAX(0,N45-1))) -> 97.229877 | U45: =MAX(0,MIN(100,U44+0.35*(58+0.6*($E$7-10)-30*MAX(0,N45-1)-20*MAX(0,O45-1)-U44))) -> 60.625502 | V45: =B45*$B$7+E45*$B$8+D45*$B$9 -> 36478 | W45: =(J45*$B$10+K45*$B$11+L45*$B$12)*$B$13/12 -> 16685 | X45: =F45*$B$19*($B$22*$B$21+$B$23+$B$24)+K45*$B$25+MAX(0,K45-$B$27)*$B$26 -> 7357.2 | Y45: =$B$14+$B$15+$B$16 -> 9000 | Z45: =IF(AND(AD45=1,AE45<-2),0.05*($F$17*$B$7+2*$G$17*$B$8+$G$17*$B$9),0)+IF(AND(AH45=1,AI45<-2),0.05*($F$18*$B$7+2*$G$18*$B$8+$G$18*$B$9),0)+IF(AND(AL45=1,AM45<-2),0.05*($F$19*$B$7+2*$G$19*$B$8+$G$19*$B$9),0)+IF(AND(AP45=1,AQ45<-2),0.05*($F$20*$B$7+2*$G$20*$B$8+$G$20*$B$9),0) -> 0 | AA45: =V45-W45-X45-Y45-R45-Z45 -> 3285.8 | AB45: =AB44+AA45 -> 155508.6 | AD45: =IF(AND($E$17>0,A45>=$E$17,AG44=0),1,0) -> 1 | AE45: =IF(AD45=1,MIN(S45-$H$17,IF($I$17="",9,T45-$I$17)),"") -> 2.8 | AF45: =IF(AD45=1,MAX(0,MIN(100,AF44+IF(AE45>=0,3,IF(AE45>=-2,-4,-10)))),AF44) -> 81 | AG45: =IF(OR(AG44=1,AND(AD45=1,AF45<25)),1,0) -> 0 | AH45: =IF(AND($E$18>0,A45>=$E$18,AK44=0),1,0) -> 1 | AI45: =IF(AH45=1,MIN(S45-$H$18,IF($I$18="",9,T45-$I$18)),"") -> 1.2298771 | AJ45: =IF(AH45=1,MAX(0,MIN(100,AJ44+IF(AI45>=0,3,IF(AI45>=-2,-4,-10)))),AJ44) -> 72 | AK45: =IF(OR(AK44=1,AND(AH45=1,AJ45<25)),1,0) -> 0 | AL45: =IF(AND($E$19>0,A45>=$E$19,AO44=0),1,0) -> 0 | AM45: =IF(AL45=1,MIN(S45-$H$19,IF($I$19="",9,T45-$I$19)),"") | AN45: =IF(AL45=1,MAX(0,MIN(100,AN44+IF(AM45>=0,3,IF(AM45>=-2,-4,-10)))),AN44) -> 60 | AO45: =IF(OR(AO44=1,AND(AL45=1,AN45<25)),1,0) -> 0 | AP45: =IF(AND($E$20>0,A45>=$E$20,AS44=0),1,0) -> 0 | AQ45: =IF(AP45=1,MIN(S45-$H$20,IF($I$20="",9,T45-$I$20)),"") | AR45: =IF(AP45=1,MAX(0,MIN(100,AR44+IF(AQ45>=0,3,IF(AQ45>=-2,-4,-10)))),AR44) -> 60 | AS45: =IF(OR(AS44=1,AND(AP45=1,AR45<25)),1,0) -> 0
A46: 8 | B46: =AD46*$F$17+AH46*$F$18+AL46*$F$19+AP46*$F$20 -> 1300 | C46: =B46/$B$6 -> 0.52 | D46: =AD46*$G$17+AH46*$G$18+AL46*$G$19+AP46*$G$20 -> 780 | E46: =2*D46 -> 1560 | F46: =ROUNDUP(D46/$B$18,0) -> 49 | G46: =MAX($B$29,ROUNDUP(E46/$B$17,0)) -> 2 | H46: =MAX(1,ROUNDUP(F46/$B$20,0)) -> 3 | I46: =$B$30+INT(D46/$B$28) -> 2 | J46: =IF($B$35=1,G45,G46) -> 2 | K46: =IF($B$35=1,H45,H46) -> 3 | L46: =IF($B$35=1,I45,I46) -> 2 | M46: =$B$17*(0.7+0.3*U45/70) -> 863.84122 | N46: =E46/(J46*M46) -> 0.90294371 | O46: =F46/(K46*$B$20) -> 0.81666667 | P46: =$F$11*IF(AND($E$11>0,A46>=$E$11),IF((A46-$E$11+1)*4.3<=$J$11*IF($E$8=1,1.5,1),-0.5,1),0)+$F$12*IF(AND($E$12>0,A46>=$E$12),IF((A46-$E$12+1)*4.3<=$J$12*IF($E$8=1,1.5,1),-0.5,1),0) -> 1.5 | Q46: =$G$11*IF(AND($E$11>0,A46>=$E$11),IF((A46-$E$11+1)*4.3<=$J$11*IF($E$8=1,1.5,1),-0.5,1),0)+$G$12*IF(AND($E$12>0,A46>=$E$12),IF((A46-$E$12+1)*4.3<=$J$12*IF($E$8=1,1.5,1),-0.5,1),0) -> 0 | R46: =IF(AND($E$11>0,A46=$E$11),$H$11,0)+IF(AND($E$11>0,A46>=$E$11),$I$11,0)+IF(AND($E$12>0,A46=$E$12),$H$12,0)+IF(AND($E$12>0,A46>=$E$12),$I$12,0) -> 150 | S46: =MAX(50,MIN(99.9,$B$31+$B$32*($E$5-10)+Q46-20*MAX(0,O46-1)-5*MAX(0,N46-1.05))) -> 94.8 | T46: =MAX(50,MIN(99.9,$B$33+$B$34*($E$6-10)+0.04*(U45-60)+P46-25*MAX(0,C46-0.85)-8*MAX(0,N46-1))) -> 97.22502 | U46: =MAX(0,MIN(100,U45+0.35*(58+0.6*($E$7-10)-30*MAX(0,N46-1)-20*MAX(0,O46-1)-U45))) -> 60.546577 | V46: =B46*$B$7+E46*$B$8+D46*$B$9 -> 36478 | W46: =(J46*$B$10+K46*$B$11+L46*$B$12)*$B$13/12 -> 16685 | X46: =F46*$B$19*($B$22*$B$21+$B$23+$B$24)+K46*$B$25+MAX(0,K46-$B$27)*$B$26 -> 7357.2 | Y46: =$B$14+$B$15+$B$16 -> 9000 | Z46: =IF(AND(AD46=1,AE46<-2),0.05*($F$17*$B$7+2*$G$17*$B$8+$G$17*$B$9),0)+IF(AND(AH46=1,AI46<-2),0.05*($F$18*$B$7+2*$G$18*$B$8+$G$18*$B$9),0)+IF(AND(AL46=1,AM46<-2),0.05*($F$19*$B$7+2*$G$19*$B$8+$G$19*$B$9),0)+IF(AND(AP46=1,AQ46<-2),0.05*($F$20*$B$7+2*$G$20*$B$8+$G$20*$B$9),0) -> 0 | AA46: =V46-W46-X46-Y46-R46-Z46 -> 3285.8 | AB46: =AB45+AA46 -> 158794.4 | AD46: =IF(AND($E$17>0,A46>=$E$17,AG45=0),1,0) -> 1 | AE46: =IF(AD46=1,MIN(S46-$H$17,IF($I$17="",9,T46-$I$17)),"") -> 2.8 | AF46: =IF(AD46=1,MAX(0,MIN(100,AF45+IF(AE46>=0,3,IF(AE46>=-2,-4,-10)))),AF45) -> 84 | AG46: =IF(OR(AG45=1,AND(AD46=1,AF46<25)),1,0) -> 0 | AH46: =IF(AND($E$18>0,A46>=$E$18,AK45=0),1,0) -> 1 | AI46: =IF(AH46=1,MIN(S46-$H$18,IF($I$18="",9,T46-$I$18)),"") -> 1.2250201 | AJ46: =IF(AH46=1,MAX(0,MIN(100,AJ45+IF(AI46>=0,3,IF(AI46>=-2,-4,-10)))),AJ45) -> 75 | AK46: =IF(OR(AK45=1,AND(AH46=1,AJ46<25)),1,0) -> 0 | AL46: =IF(AND($E$19>0,A46>=$E$19,AO45=0),1,0) -> 0 | AM46: =IF(AL46=1,MIN(S46-$H$19,IF($I$19="",9,T46-$I$19)),"") | AN46: =IF(AL46=1,MAX(0,MIN(100,AN45+IF(AM46>=0,3,IF(AM46>=-2,-4,-10)))),AN45) -> 60 | AO46: =IF(OR(AO45=1,AND(AL46=1,AN46<25)),1,0) -> 0 | AP46: =IF(AND($E$20>0,A46>=$E$20,AS45=0),1,0) -> 0 | AQ46: =IF(AP46=1,MIN(S46-$H$20,IF($I$20="",9,T46-$I$20)),"") | AR46: =IF(AP46=1,MAX(0,MIN(100,AR45+IF(AQ46>=0,3,IF(AQ46>=-2,-4,-10)))),AR45) -> 60 | AS46: =IF(OR(AS45=1,AND(AP46=1,AR46<25)),1,0) -> 0
A47: 9 | B47: =AD47*$F$17+AH47*$F$18+AL47*$F$19+AP47*$F$20 -> 1800 | C47: =B47/$B$6 -> 0.72 | D47: =AD47*$G$17+AH47*$G$18+AL47*$G$19+AP47*$G$20 -> 1030 | E47: =2*D47 -> 2060 | F47: =ROUNDUP(D47/$B$18,0) -> 65 | G47: =MAX($B$29,ROUNDUP(E47/$B$17,0)) -> 3 | H47: =MAX(1,ROUNDUP(F47/$B$20,0)) -> 4 | I47: =$B$30+INT(D47/$B$28) -> 2 | J47: =IF($B$35=1,G46,G47) -> 3 | K47: =IF($B$35=1,H46,H47) -> 4 | L47: =IF($B$35=1,I46,I47) -> 2 | M47: =$B$17*(0.7+0.3*U46/70) -> 863.5368 | N47: =E47/(J47*M47) -> 0.7951794 | O47: =F47/(K47*$B$20) -> 0.8125 | P47: =$F$11*IF(AND($E$11>0,A47>=$E$11),IF((A47-$E$11+1)*4.3<=$J$11*IF($E$8=1,1.5,1),-0.5,1),0)+$F$12*IF(AND($E$12>0,A47>=$E$12),IF((A47-$E$12+1)*4.3<=$J$12*IF($E$8=1,1.5,1),-0.5,1),0) -> 1.5 | Q47: =$G$11*IF(AND($E$11>0,A47>=$E$11),IF((A47-$E$11+1)*4.3<=$J$11*IF($E$8=1,1.5,1),-0.5,1),0)+$G$12*IF(AND($E$12>0,A47>=$E$12),IF((A47-$E$12+1)*4.3<=$J$12*IF($E$8=1,1.5,1),-0.5,1),0) -> 0 | R47: =IF(AND($E$11>0,A47=$E$11),$H$11,0)+IF(AND($E$11>0,A47>=$E$11),$I$11,0)+IF(AND($E$12>0,A47=$E$12),$H$12,0)+IF(AND($E$12>0,A47>=$E$12),$I$12,0) -> 150 | S47: =MAX(50,MIN(99.9,$B$31+$B$32*($E$5-10)+Q47-20*MAX(0,O47-1)-5*MAX(0,N47-1.05))) -> 94.8 | T47: =MAX(50,MIN(99.9,$B$33+$B$34*($E$6-10)+0.04*(U46-60)+P47-25*MAX(0,C47-0.85)-8*MAX(0,N47-1))) -> 97.221863 | U47: =MAX(0,MIN(100,U46+0.35*(58+0.6*($E$7-10)-30*MAX(0,N47-1)-20*MAX(0,O47-1)-U46))) -> 60.495275 | V47: =B47*$B$7+E47*$B$8+D47*$B$9 -> 48628 | W47: =(J47*$B$10+K47*$B$11+L47*$B$12)*$B$13/12 -> 21240.833 | X47: =F47*$B$19*($B$22*$B$21+$B$23+$B$24)+K47*$B$25+MAX(0,K47-$B$27)*$B$26 -> 11882 | Y47: =$B$14+$B$15+$B$16 -> 9000 | Z47: =IF(AND(AD47=1,AE47<-2),0.05*($F$17*$B$7+2*$G$17*$B$8+$G$17*$B$9),0)+IF(AND(AH47=1,AI47<-2),0.05*($F$18*$B$7+2*$G$18*$B$8+$G$18*$B$9),0)+IF(AND(AL47=1,AM47<-2),0.05*($F$19*$B$7+2*$G$19*$B$8+$G$19*$B$9),0)+IF(AND(AP47=1,AQ47<-2),0.05*($F$20*$B$7+2*$G$20*$B$8+$G$20*$B$9),0) -> 0 | AA47: =V47-W47-X47-Y47-R47-Z47 -> 6355.1667 | AB47: =AB46+AA47 -> 165149.57 | AD47: =IF(AND($E$17>0,A47>=$E$17,AG46=0),1,0) -> 1 | AE47: =IF(AD47=1,MIN(S47-$H$17,IF($I$17="",9,T47-$I$17)),"") -> 2.8 | AF47: =IF(AD47=1,MAX(0,MIN(100,AF46+IF(AE47>=0,3,IF(AE47>=-2,-4,-10)))),AF46) -> 87 | AG47: =IF(OR(AG46=1,AND(AD47=1,AF47<25)),1,0) -> 0 | AH47: =IF(AND($E$18>0,A47>=$E$18,AK46=0),1,0) -> 1 | AI47: =IF(AH47=1,MIN(S47-$H$18,IF($I$18="",9,T47-$I$18)),"") -> 1.2218631 | AJ47: =IF(AH47=1,MAX(0,MIN(100,AJ46+IF(AI47>=0,3,IF(AI47>=-2,-4,-10)))),AJ46) -> 78 | AK47: =IF(OR(AK46=1,AND(AH47=1,AJ47<25)),1,0) -> 0 | AL47: =IF(AND($E$19>0,A47>=$E$19,AO46=0),1,0) -> 1 | AM47: =IF(AL47=1,MIN(S47-$H$19,IF($I$19="",9,T47-$I$19)),"") -> 0.22186306 | AN47: =IF(AL47=1,MAX(0,MIN(100,AN46+IF(AM47>=0,3,IF(AM47>=-2,-4,-10)))),AN46) -> 63 | AO47: =IF(OR(AO46=1,AND(AL47=1,AN47<25)),1,0) -> 0 | AP47: =IF(AND($E$20>0,A47>=$E$20,AS46=0),1,0) -> 0 | AQ47: =IF(AP47=1,MIN(S47-$H$20,IF($I$20="",9,T47-$I$20)),"") | AR47: =IF(AP47=1,MAX(0,MIN(100,AR46+IF(AQ47>=0,3,IF(AQ47>=-2,-4,-10)))),AR46) -> 60 | AS47: =IF(OR(AS46=1,AND(AP47=1,AR47<25)),1,0) -> 0
A48: 10 | B48: =AD48*$F$17+AH48*$F$18+AL48*$F$19+AP48*$F$20 -> 1800 | C48: =B48/$B$6 -> 0.72 | D48: =AD48*$G$17+AH48*$G$18+AL48*$G$19+AP48*$G$20 -> 1030 | E48: =2*D48 -> 2060 | F48: =ROUNDUP(D48/$B$18,0) -> 65 | G48: =MAX($B$29,ROUNDUP(E48/$B$17,0)) -> 3 | H48: =MAX(1,ROUNDUP(F48/$B$20,0)) -> 4 | I48: =$B$30+INT(D48/$B$28) -> 2 | J48: =IF($B$35=1,G47,G48) -> 3 | K48: =IF($B$35=1,H47,H48) -> 4 | L48: =IF($B$35=1,I47,I48) -> 2 | M48: =$B$17*(0.7+0.3*U47/70) -> 863.33892 | N48: =E48/(J48*M48) -> 0.79536165 | O48: =F48/(K48*$B$20) -> 0.8125 | P48: =$F$11*IF(AND($E$11>0,A48>=$E$11),IF((A48-$E$11+1)*4.3<=$J$11*IF($E$8=1,1.5,1),-0.5,1),0)+$F$12*IF(AND($E$12>0,A48>=$E$12),IF((A48-$E$12+1)*4.3<=$J$12*IF($E$8=1,1.5,1),-0.5,1),0) -> 1.5 | Q48: =$G$11*IF(AND($E$11>0,A48>=$E$11),IF((A48-$E$11+1)*4.3<=$J$11*IF($E$8=1,1.5,1),-0.5,1),0)+$G$12*IF(AND($E$12>0,A48>=$E$12),IF((A48-$E$12+1)*4.3<=$J$12*IF($E$8=1,1.5,1),-0.5,1),0) -> 0 | R48: =IF(AND($E$11>0,A48=$E$11),$H$11,0)+IF(AND($E$11>0,A48>=$E$11),$I$11,0)+IF(AND($E$12>0,A48=$E$12),$H$12,0)+IF(AND($E$12>0,A48>=$E$12),$I$12,0) -> 150 | S48: =MAX(50,MIN(99.9,$B$31+$B$32*($E$5-10)+Q48-20*MAX(0,O48-1)-5*MAX(0,N48-1.05))) -> 94.8 | T48: =MAX(50,MIN(99.9,$B$33+$B$34*($E$6-10)+0.04*(U47-60)+P48-25*MAX(0,C48-0.85)-8*MAX(0,N48-1))) -> 97.219811 | U48: =MAX(0,MIN(100,U47+0.35*(58+0.6*($E$7-10)-30*MAX(0,N48-1)-20*MAX(0,O48-1)-U47))) -> 60.461929 | V48: =B48*$B$7+E48*$B$8+D48*$B$9 -> 48628 | W48: =(J48*$B$10+K48*$B$11+L48*$B$12)*$B$13/12 -> 21240.833 | X48: =F48*$B$19*($B$22*$B$21+$B$23+$B$24)+K48*$B$25+MAX(0,K48-$B$27)*$B$26 -> 11882 | Y48: =$B$14+$B$15+$B$16 -> 9000 | Z48: =IF(AND(AD48=1,AE48<-2),0.05*($F$17*$B$7+2*$G$17*$B$8+$G$17*$B$9),0)+IF(AND(AH48=1,AI48<-2),0.05*($F$18*$B$7+2*$G$18*$B$8+$G$18*$B$9),0)+IF(AND(AL48=1,AM48<-2),0.05*($F$19*$B$7+2*$G$19*$B$8+$G$19*$B$9),0)+IF(AND(AP48=1,AQ48<-2),0.05*($F$20*$B$7+2*$G$20*$B$8+$G$20*$B$9),0) -> 0 | AA48: =V48-W48-X48-Y48-R48-Z48 -> 6355.1667 | AB48: =AB47+AA48 -> 171504.73 | AD48: =IF(AND($E$17>0,A48>=$E$17,AG47=0),1,0) -> 1 | AE48: =IF(AD48=1,MIN(S48-$H$17,IF($I$17="",9,T48-$I$17)),"") -> 2.8 | AF48: =IF(AD48=1,MAX(0,MIN(100,AF47+IF(AE48>=0,3,IF(AE48>=-2,-4,-10)))),AF47) -> 90 | AG48: =IF(OR(AG47=1,AND(AD48=1,AF48<25)),1,0) -> 0 | AH48: =IF(AND($E$18>0,A48>=$E$18,AK47=0),1,0) -> 1 | AI48: =IF(AH48=1,MIN(S48-$H$18,IF($I$18="",9,T48-$I$18)),"") -> 1.219811 | AJ48: =IF(AH48=1,MAX(0,MIN(100,AJ47+IF(AI48>=0,3,IF(AI48>=-2,-4,-10)))),AJ47) -> 81 | AK48: =IF(OR(AK47=1,AND(AH48=1,AJ48<25)),1,0) -> 0 | AL48: =IF(AND($E$19>0,A48>=$E$19,AO47=0),1,0) -> 1 | AM48: =IF(AL48=1,MIN(S48-$H$19,IF($I$19="",9,T48-$I$19)),"") -> 0.21981099 | AN48: =IF(AL48=1,MAX(0,MIN(100,AN47+IF(AM48>=0,3,IF(AM48>=-2,-4,-10)))),AN47) -> 66 | AO48: =IF(OR(AO47=1,AND(AL48=1,AN48<25)),1,0) -> 0 | AP48: =IF(AND($E$20>0,A48>=$E$20,AS47=0),1,0) -> 0 | AQ48: =IF(AP48=1,MIN(S48-$H$20,IF($I$20="",9,T48-$I$20)),"") | AR48: =IF(AP48=1,MAX(0,MIN(100,AR47+IF(AQ48>=0,3,IF(AQ48>=-2,-4,-10)))),AR47) -> 60 | AS48: =IF(OR(AS47=1,AND(AP48=1,AR48<25)),1,0) -> 0
A49: 11 | B49: =AD49*$F$17+AH49*$F$18+AL49*$F$19+AP49*$F$20 -> 1800 | C49: =B49/$B$6 -> 0.72 | D49: =AD49*$G$17+AH49*$G$18+AL49*$G$19+AP49*$G$20 -> 1030 | E49: =2*D49 -> 2060 | F49: =ROUNDUP(D49/$B$18,0) -> 65 | G49: =MAX($B$29,ROUNDUP(E49/$B$17,0)) -> 3 | H49: =MAX(1,ROUNDUP(F49/$B$20,0)) -> 4 | I49: =$B$30+INT(D49/$B$28) -> 2 | J49: =IF($B$35=1,G48,G49) -> 3 | K49: =IF($B$35=1,H48,H49) -> 4 | L49: =IF($B$35=1,I48,I49) -> 2 | M49: =$B$17*(0.7+0.3*U48/70) -> 863.2103 | N49: =E49/(J49*M49) -> 0.79548016 | O49: =F49/(K49*$B$20) -> 0.8125 | P49: =$F$11*IF(AND($E$11>0,A49>=$E$11),IF((A49-$E$11+1)*4.3<=$J$11*IF($E$8=1,1.5,1),-0.5,1),0)+$F$12*IF(AND($E$12>0,A49>=$E$12),IF((A49-$E$12+1)*4.3<=$J$12*IF($E$8=1,1.5,1),-0.5,1),0) -> 1.5 | Q49: =$G$11*IF(AND($E$11>0,A49>=$E$11),IF((A49-$E$11+1)*4.3<=$J$11*IF($E$8=1,1.5,1),-0.5,1),0)+$G$12*IF(AND($E$12>0,A49>=$E$12),IF((A49-$E$12+1)*4.3<=$J$12*IF($E$8=1,1.5,1),-0.5,1),0) -> 0 | R49: =IF(AND($E$11>0,A49=$E$11),$H$11,0)+IF(AND($E$11>0,A49>=$E$11),$I$11,0)+IF(AND($E$12>0,A49=$E$12),$H$12,0)+IF(AND($E$12>0,A49>=$E$12),$I$12,0) -> 150 | S49: =MAX(50,MIN(99.9,$B$31+$B$32*($E$5-10)+Q49-20*MAX(0,O49-1)-5*MAX(0,N49-1.05))) -> 94.8 | T49: =MAX(50,MIN(99.9,$B$33+$B$34*($E$6-10)+0.04*(U48-60)+P49-25*MAX(0,C49-0.85)-8*MAX(0,N49-1))) -> 97.218477 | U49: =MAX(0,MIN(100,U48+0.35*(58+0.6*($E$7-10)-30*MAX(0,N49-1)-20*MAX(0,O49-1)-U48))) -> 60.440254 | V49: =B49*$B$7+E49*$B$8+D49*$B$9 -> 48628 | W49: =(J49*$B$10+K49*$B$11+L49*$B$12)*$B$13/12 -> 21240.833 | X49: =F49*$B$19*($B$22*$B$21+$B$23+$B$24)+K49*$B$25+MAX(0,K49-$B$27)*$B$26 -> 11882 | Y49: =$B$14+$B$15+$B$16 -> 9000 | Z49: =IF(AND(AD49=1,AE49<-2),0.05*($F$17*$B$7+2*$G$17*$B$8+$G$17*$B$9),0)+IF(AND(AH49=1,AI49<-2),0.05*($F$18*$B$7+2*$G$18*$B$8+$G$18*$B$9),0)+IF(AND(AL49=1,AM49<-2),0.05*($F$19*$B$7+2*$G$19*$B$8+$G$19*$B$9),0)+IF(AND(AP49=1,AQ49<-2),0.05*($F$20*$B$7+2*$G$20*$B$8+$G$20*$B$9),0) -> 0 | AA49: =V49-W49-X49-Y49-R49-Z49 -> 6355.1667 | AB49: =AB48+AA49 -> 177859.9 | AD49: =IF(AND($E$17>0,A49>=$E$17,AG48=0),1,0) -> 1 | AE49: =IF(AD49=1,MIN(S49-$H$17,IF($I$17="",9,T49-$I$17)),"") -> 2.8 | AF49: =IF(AD49=1,MAX(0,MIN(100,AF48+IF(AE49>=0,3,IF(AE49>=-2,-4,-10)))),AF48) -> 93 | AG49: =IF(OR(AG48=1,AND(AD49=1,AF49<25)),1,0) -> 0 | AH49: =IF(AND($E$18>0,A49>=$E$18,AK48=0),1,0) -> 1 | AI49: =IF(AH49=1,MIN(S49-$H$18,IF($I$18="",9,T49-$I$18)),"") -> 1.2184771 | AJ49: =IF(AH49=1,MAX(0,MIN(100,AJ48+IF(AI49>=0,3,IF(AI49>=-2,-4,-10)))),AJ48) -> 84 | AK49: =IF(OR(AK48=1,AND(AH49=1,AJ49<25)),1,0) -> 0 | AL49: =IF(AND($E$19>0,A49>=$E$19,AO48=0),1,0) -> 1 | AM49: =IF(AL49=1,MIN(S49-$H$19,IF($I$19="",9,T49-$I$19)),"") -> 0.21847714 | AN49: =IF(AL49=1,MAX(0,MIN(100,AN48+IF(AM49>=0,3,IF(AM49>=-2,-4,-10)))),AN48) -> 69 | AO49: =IF(OR(AO48=1,AND(AL49=1,AN49<25)),1,0) -> 0 | AP49: =IF(AND($E$20>0,A49>=$E$20,AS48=0),1,0) -> 0 | AQ49: =IF(AP49=1,MIN(S49-$H$20,IF($I$20="",9,T49-$I$20)),"") | AR49: =IF(AP49=1,MAX(0,MIN(100,AR48+IF(AQ49>=0,3,IF(AQ49>=-2,-4,-10)))),AR48) -> 60 | AS49: =IF(OR(AS48=1,AND(AP49=1,AR49<25)),1,0) -> 0
A50: 12 | B50: =AD50*$F$17+AH50*$F$18+AL50*$F$19+AP50*$F$20 -> 1800 | C50: =B50/$B$6 -> 0.72 | D50: =AD50*$G$17+AH50*$G$18+AL50*$G$19+AP50*$G$20 -> 1030 | E50: =2*D50 -> 2060 | F50: =ROUNDUP(D50/$B$18,0) -> 65 | G50: =MAX($B$29,ROUNDUP(E50/$B$17,0)) -> 3 | H50: =MAX(1,ROUNDUP(F50/$B$20,0)) -> 4 | I50: =$B$30+INT(D50/$B$28) -> 2 | J50: =IF($B$35=1,G49,G50) -> 3 | K50: =IF($B$35=1,H49,H50) -> 4 | L50: =IF($B$35=1,I49,I50) -> 2 | M50: =$B$17*(0.7+0.3*U49/70) -> 863.12669 | N50: =E50/(J50*M50) -> 0.79555721 | O50: =F50/(K50*$B$20) -> 0.8125 | P50: =$F$11*IF(AND($E$11>0,A50>=$E$11),IF((A50-$E$11+1)*4.3<=$J$11*IF($E$8=1,1.5,1),-0.5,1),0)+$F$12*IF(AND($E$12>0,A50>=$E$12),IF((A50-$E$12+1)*4.3<=$J$12*IF($E$8=1,1.5,1),-0.5,1),0) -> 1.5 | Q50: =$G$11*IF(AND($E$11>0,A50>=$E$11),IF((A50-$E$11+1)*4.3<=$J$11*IF($E$8=1,1.5,1),-0.5,1),0)+$G$12*IF(AND($E$12>0,A50>=$E$12),IF((A50-$E$12+1)*4.3<=$J$12*IF($E$8=1,1.5,1),-0.5,1),0) -> 0 | R50: =IF(AND($E$11>0,A50=$E$11),$H$11,0)+IF(AND($E$11>0,A50>=$E$11),$I$11,0)+IF(AND($E$12>0,A50=$E$12),$H$12,0)+IF(AND($E$12>0,A50>=$E$12),$I$12,0) -> 150 | S50: =MAX(50,MIN(99.9,$B$31+$B$32*($E$5-10)+Q50-20*MAX(0,O50-1)-5*MAX(0,N50-1.05))) -> 94.8 | T50: =MAX(50,MIN(99.9,$B$33+$B$34*($E$6-10)+0.04*(U49-60)+P50-25*MAX(0,C50-0.85)-8*MAX(0,N50-1))) -> 97.21761 | U50: =MAX(0,MIN(100,U49+0.35*(58+0.6*($E$7-10)-30*MAX(0,N50-1)-20*MAX(0,O50-1)-U49))) -> 60.426165 | V50: =B50*$B$7+E50*$B$8+D50*$B$9 -> 48628 | W50: =(J50*$B$10+K50*$B$11+L50*$B$12)*$B$13/12 -> 21240.833 | X50: =F50*$B$19*($B$22*$B$21+$B$23+$B$24)+K50*$B$25+MAX(0,K50-$B$27)*$B$26 -> 11882 | Y50: =$B$14+$B$15+$B$16 -> 9000 | Z50: =IF(AND(AD50=1,AE50<-2),0.05*($F$17*$B$7+2*$G$17*$B$8+$G$17*$B$9),0)+IF(AND(AH50=1,AI50<-2),0.05*($F$18*$B$7+2*$G$18*$B$8+$G$18*$B$9),0)+IF(AND(AL50=1,AM50<-2),0.05*($F$19*$B$7+2*$G$19*$B$8+$G$19*$B$9),0)+IF(AND(AP50=1,AQ50<-2),0.05*($F$20*$B$7+2*$G$20*$B$8+$G$20*$B$9),0) -> 0 | AA50: =V50-W50-X50-Y50-R50-Z50 -> 6355.1667 | AB50: =AB49+AA50 -> 184215.07 | AD50: =IF(AND($E$17>0,A50>=$E$17,AG49=0),1,0) -> 1 | AE50: =IF(AD50=1,MIN(S50-$H$17,IF($I$17="",9,T50-$I$17)),"") -> 2.8 | AF50: =IF(AD50=1,MAX(0,MIN(100,AF49+IF(AE50>=0,3,IF(AE50>=-2,-4,-10)))),AF49) -> 96 | AG50: =IF(OR(AG49=1,AND(AD50=1,AF50<25)),1,0) -> 0 | AH50: =IF(AND($E$18>0,A50>=$E$18,AK49=0),1,0) -> 1 | AI50: =IF(AH50=1,MIN(S50-$H$18,IF($I$18="",9,T50-$I$18)),"") -> 1.2176101 | AJ50: =IF(AH50=1,MAX(0,MIN(100,AJ49+IF(AI50>=0,3,IF(AI50>=-2,-4,-10)))),AJ49) -> 87 | AK50: =IF(OR(AK49=1,AND(AH50=1,AJ50<25)),1,0) -> 0 | AL50: =IF(AND($E$19>0,A50>=$E$19,AO49=0),1,0) -> 1 | AM50: =IF(AL50=1,MIN(S50-$H$19,IF($I$19="",9,T50-$I$19)),"") -> 0.21761014 | AN50: =IF(AL50=1,MAX(0,MIN(100,AN49+IF(AM50>=0,3,IF(AM50>=-2,-4,-10)))),AN49) -> 72 | AO50: =IF(OR(AO49=1,AND(AL50=1,AN50<25)),1,0) -> 0 | AP50: =IF(AND($E$20>0,A50>=$E$20,AS49=0),1,0) -> 0 | AQ50: =IF(AP50=1,MIN(S50-$H$20,IF($I$20="",9,T50-$I$20)),"") | AR50: =IF(AP50=1,MAX(0,MIN(100,AR49+IF(AQ50>=0,3,IF(AQ50>=-2,-4,-10)))),AR49) -> 60 | AS50: =IF(OR(AS49=1,AND(AP50=1,AR50<25)),1,0) -> 0
A51: 13 | B51: =AD51*$F$17+AH51*$F$18+AL51*$F$19+AP51*$F$20 -> 1800 | C51: =B51/$B$6 -> 0.72 | D51: =AD51*$G$17+AH51*$G$18+AL51*$G$19+AP51*$G$20 -> 1030 | E51: =2*D51 -> 2060 | F51: =ROUNDUP(D51/$B$18,0) -> 65 | G51: =MAX($B$29,ROUNDUP(E51/$B$17,0)) -> 3 | H51: =MAX(1,ROUNDUP(F51/$B$20,0)) -> 4 | I51: =$B$30+INT(D51/$B$28) -> 2 | J51: =IF($B$35=1,G50,G51) -> 3 | K51: =IF($B$35=1,H50,H51) -> 4 | L51: =IF($B$35=1,I50,I51) -> 2 | M51: =$B$17*(0.7+0.3*U50/70) -> 863.07235 | N51: =E51/(J51*M51) -> 0.79560731 | O51: =F51/(K51*$B$20) -> 0.8125 | P51: =$F$11*IF(AND($E$11>0,A51>=$E$11),IF((A51-$E$11+1)*4.3<=$J$11*IF($E$8=1,1.5,1),-0.5,1),0)+$F$12*IF(AND($E$12>0,A51>=$E$12),IF((A51-$E$12+1)*4.3<=$J$12*IF($E$8=1,1.5,1),-0.5,1),0) -> 1.5 | Q51: =$G$11*IF(AND($E$11>0,A51>=$E$11),IF((A51-$E$11+1)*4.3<=$J$11*IF($E$8=1,1.5,1),-0.5,1),0)+$G$12*IF(AND($E$12>0,A51>=$E$12),IF((A51-$E$12+1)*4.3<=$J$12*IF($E$8=1,1.5,1),-0.5,1),0) -> 0 | R51: =IF(AND($E$11>0,A51=$E$11),$H$11,0)+IF(AND($E$11>0,A51>=$E$11),$I$11,0)+IF(AND($E$12>0,A51=$E$12),$H$12,0)+IF(AND($E$12>0,A51>=$E$12),$I$12,0) -> 150 | S51: =MAX(50,MIN(99.9,$B$31+$B$32*($E$5-10)+Q51-20*MAX(0,O51-1)-5*MAX(0,N51-1.05))) -> 94.8 | T51: =MAX(50,MIN(99.9,$B$33+$B$34*($E$6-10)+0.04*(U50-60)+P51-25*MAX(0,C51-0.85)-8*MAX(0,N51-1))) -> 97.217047 | U51: =MAX(0,MIN(100,U50+0.35*(58+0.6*($E$7-10)-30*MAX(0,N51-1)-20*MAX(0,O51-1)-U50))) -> 60.417007 | V51: =B51*$B$7+E51*$B$8+D51*$B$9 -> 48628 | W51: =(J51*$B$10+K51*$B$11+L51*$B$12)*$B$13/12 -> 21240.833 | X51: =F51*$B$19*($B$22*$B$21+$B$23+$B$24)+K51*$B$25+MAX(0,K51-$B$27)*$B$26 -> 11882 | Y51: =$B$14+$B$15+$B$16 -> 9000 | Z51: =IF(AND(AD51=1,AE51<-2),0.05*($F$17*$B$7+2*$G$17*$B$8+$G$17*$B$9),0)+IF(AND(AH51=1,AI51<-2),0.05*($F$18*$B$7+2*$G$18*$B$8+$G$18*$B$9),0)+IF(AND(AL51=1,AM51<-2),0.05*($F$19*$B$7+2*$G$19*$B$8+$G$19*$B$9),0)+IF(AND(AP51=1,AQ51<-2),0.05*($F$20*$B$7+2*$G$20*$B$8+$G$20*$B$9),0) -> 0 | AA51: =V51-W51-X51-Y51-R51-Z51 -> 6355.1667 | AB51: =AB50+AA51 -> 190570.23 | AD51: =IF(AND($E$17>0,A51>=$E$17,AG50=0),1,0) -> 1 | AE51: =IF(AD51=1,MIN(S51-$H$17,IF($I$17="",9,T51-$I$17)),"") -> 2.8 | AF51: =IF(AD51=1,MAX(0,MIN(100,AF50+IF(AE51>=0,3,IF(AE51>=-2,-4,-10)))),AF50) -> 99 | AG51: =IF(OR(AG50=1,AND(AD51=1,AF51<25)),1,0) -> 0 | AH51: =IF(AND($E$18>0,A51>=$E$18,AK50=0),1,0) -> 1 | AI51: =IF(AH51=1,MIN(S51-$H$18,IF($I$18="",9,T51-$I$18)),"") -> 1.2170466 | AJ51: =IF(AH51=1,MAX(0,MIN(100,AJ50+IF(AI51>=0,3,IF(AI51>=-2,-4,-10)))),AJ50) -> 90 | AK51: =IF(OR(AK50=1,AND(AH51=1,AJ51<25)),1,0) -> 0 | AL51: =IF(AND($E$19>0,A51>=$E$19,AO50=0),1,0) -> 1 | AM51: =IF(AL51=1,MIN(S51-$H$19,IF($I$19="",9,T51-$I$19)),"") -> 0.21704659 | AN51: =IF(AL51=1,MAX(0,MIN(100,AN50+IF(AM51>=0,3,IF(AM51>=-2,-4,-10)))),AN50) -> 75 | AO51: =IF(OR(AO50=1,AND(AL51=1,AN51<25)),1,0) -> 0 | AP51: =IF(AND($E$20>0,A51>=$E$20,AS50=0),1,0) -> 0 | AQ51: =IF(AP51=1,MIN(S51-$H$20,IF($I$20="",9,T51-$I$20)),"") | AR51: =IF(AP51=1,MAX(0,MIN(100,AR50+IF(AQ51>=0,3,IF(AQ51>=-2,-4,-10)))),AR50) -> 60 | AS51: =IF(OR(AS50=1,AND(AP51=1,AR51<25)),1,0) -> 0
... A62: 24 | B62: =AD62*$F$17+AH62*$F$18+AL62*$F$19+AP62*$F$20 -> 1800 | C62: =B62/$B$6 -> 0.72 | D62: =AD62*$G$17+AH62*$G$18+AL62*$G$19+AP62*$G$20 -> 1030 | E62: =2*D62 -> 2060 | F62: =ROUNDUP(D62/$B$18,0) -> 65 | G62: =MAX($B$29,ROUNDUP(E62/$B$17,0)) -> 3 | H62: =MAX(1,ROUNDUP(F62/$B$20,0)) -> 4 | I62: =$B$30+INT(D62/$B$28) -> 2 | J62: =IF($B$35=1,G61,G62) -> 3 | K62: =IF($B$35=1,H61,H62) -> 4 | L62: =IF($B$35=1,I61,I62) -> 2 | M62: =$B$17*(0.7+0.3*U61/70) -> 862.97231 | N62: =E62/(J62*M62) -> 0.79569953 | O62: =F62/(K62*$B$20) -> 0.8125 | P62: =$F$11*IF(AND($E$11>0,A62>=$E$11),IF((A62-$E$11+1)*4.3<=$J$11*IF($E$8=1,1.5,1),-0.5,1),0)+$F$12*IF(AND($E$12>0,A62>=$E$12),IF((A62-$E$12+1)*4.3<=$J$12*IF($E$8=1,1.5,1),-0.5,1),0) -> 1.5 | Q62: =$G$11*IF(AND($E$11>0,A62>=$E$11),IF((A62-$E$11+1)*4.3<=$J$11*IF($E$8=1,1.5,1),-0.5,1),0)+$G$12*IF(AND($E$12>0,A62>=$E$12),IF((A62-$E$12+1)*4.3<=$J$12*IF($E$8=1,1.5,1),-0.5,1),0) -> 0 | R62: =IF(AND($E$11>0,A62=$E$11),$H$11,0)+IF(AND($E$11>0,A62>=$E$11),$I$11,0)+IF(AND($E$12>0,A62=$E$12),$H$12,0)+IF(AND($E$12>0,A62>=$E$12),$I$12,0) -> 150 | S62: =MAX(50,MIN(99.9,$B$31+$B$32*($E$5-10)+Q62-20*MAX(0,O62-1)-5*MAX(0,N62-1.05))) -> 94.8 | T62: =MAX(50,MIN(99.9,$B$33+$B$34*($E$6-10)+0.04*(U61-60)+P62-25*MAX(0,C62-0.85)-8*MAX(0,N62-1))) -> 97.216009 | U62: =MAX(0,MIN(100,U61+0.35*(58+0.6*($E$7-10)-30*MAX(0,N62-1)-20*MAX(0,O62-1)-U61))) -> 60.400149 | V62: =B62*$B$7+E62*$B$8+D62*$B$9 -> 48628 | W62: =(J62*$B$10+K62*$B$11+L62*$B$12)*$B$13/12 -> 21240.833 | X62: =F62*$B$19*($B$22*$B$21+$B$23+$B$24)+K62*$B$25+MAX(0,K62-$B$27)*$B$26 -> 11882 | Y62: =$B$14+$B$15+$B$16 -> 9000 | Z62: =IF(AND(AD62=1,AE62<-2),0.05*($F$17*$B$7+2*$G$17*$B$8+$G$17*$B$9),0)+IF(AND(AH62=1,AI62<-2),0.05*($F$18*$B$7+2*$G$18*$B$8+$G$18*$B$9),0)+IF(AND(AL62=1,AM62<-2),0.05*($F$19*$B$7+2*$G$19*$B$8+$G$19*$B$9),0)+IF(AND(AP62=1,AQ62<-2),0.05*($F$20*$B$7+2*$G$20*$B$8+$G$20*$B$9),0) -> 0 | AA62: =V62-W62-X62-Y62-R62-Z62 -> 6355.1667 | AB62: =AB61+AA62 -> 260477.07 | AD62: =IF(AND($E$17>0,A62>=$E$17,AG61=0),1,0) -> 1 | AE62: =IF(AD62=1,MIN(S62-$H$17,IF($I$17="",9,T62-$I$17)),"") -> 2.8 | AF62: =IF(AD62=1,MAX(0,MIN(100,AF61+IF(AE62>=0,3,IF(AE62>=-2,-4,-10)))),AF61) -> 100 | AG62: =IF(OR(AG61=1,AND(AD62=1,AF62<25)),1,0) -> 0 | AH62: =IF(AND($E$18>0,A62>=$E$18,AK61=0),1,0) -> 1 | AI62: =IF(AH62=1,MIN(S62-$H$18,IF($I$18="",9,T62-$I$18)),"") -> 1.2160092 | AJ62: =IF(AH62=1,MAX(0,MIN(100,AJ61+IF(AI62>=0,3,IF(AI62>=-2,-4,-10)))),AJ61) -> 100 | AK62: =IF(OR(AK61=1,AND(AH62=1,AJ62<25)),1,0) -> 0 | AL62: =IF(AND($E$19>0,A62>=$E$19,AO61=0),1,0) -> 1 | AM62: =IF(AL62=1,MIN(S62-$H$19,IF($I$19="",9,T62-$I$19)),"") -> 0.21600916 | AN62: =IF(AL62=1,MAX(0,MIN(100,AN61+IF(AM62>=0,3,IF(AM62>=-2,-4,-10)))),AN61) -> 100 | AO62: =IF(OR(AO61=1,AND(AL62=1,AN62<25)),1,0) -> 0 | AP62: =IF(AND($E$20>0,A62>=$E$20,AS61=0),1,0) -> 0 | AQ62: =IF(AP62=1,MIN(S62-$H$20,IF($I$20="",9,T62-$I$20)),"") | AR62: =IF(AP62=1,MAX(0,MIN(100,AR61+IF(AQ62>=0,3,IF(AQ62>=-2,-4,-10)))),AR61) -> 60 | AS62: =IF(OR(AS61=1,AND(AP62=1,AR62<25)),1,0) -> 0
